Workbook

Sheet README
A1: Platzi FP&A Financial Model
A2: WP40 deliverable D1. Built by work/WP40_model/build_model.py -- rerun that script to regenerate this file from db/platzi.duckdb + the WP21/WP31 sheet_inputs.csv exports.
A4: Purpose
B5: This workbook holds the assumptions, unit economics and scenario model for Platzi's FP&A take-home
B6: challenge, with every number traceable to a formula, an assumption ID, or a named SQL mart export.
B7: The heavy data work (fact tables, MRR bridge, retention, NDR decomposition, CAC/LTV synthesis, the
B8: scenario simulation engine) lives in the SQL/DuckDB pipeline (sql/staging -> sql/intermediate ->
B9: sql/marts, plus sql/python_models/scenarios.py). This Sheet consumes that pipeline's outputs as
B10: 'Data_*' tabs (verbatim exports of named marts) and rebuilds the assumptions, unit-economics and
B11: scenario CALCULATIONS on top of them with visible spreadsheet formulas, per the 2026-09-26 update
B12: to Docs/Deliverables_Framework.md (D1): 'the data and calculation layer is SQL ... a small Google
B13: Sheet holds Assumptions, Unit Economics and Scenarios with visible formulas, fed by mart exports.'
A15: Tab map
A16: Tab | B16: Contents
A17: README | B17: This tab.
A18: Assumptions | B18: Every driver with an ID (A-xx/D-xx/A2-xx/S-xx), value, unit, source, note. Scenario selector, GM-basis selector, lifetime-cap, benchmarks, starting stock, scenario engine drivers, and the full WP21/WP31 assumption registers.
A19: Data_MRR | B19: Monthly MRR bridge by segment (mart_mrr_bridge): opening/new/expansion/contraction/churn/closing MRR + active customers, Jan-23..Apr-24.
A20: Data_Costs | B20: Monthly marketing spend by segment x channel (stg_marketing_spend), support costs by category (stg_support_costs), and new paying customers by month x segment (mart_a2_01_new_paying_customers).
A21: Data_Survival | B21: Logo and $ survival curves by segment, k=0..15 months (mart_a2_10_survival_curve).
A22: Answers_Q1_Q4 | B22: The 4 ad-hoc answers. Q1 (MRR) and Q3 (active subs) are rebuilt with formulas from Data_MRR / a small Q3 data block. Q2 (Q1-24 retention) and Q4 (NDR T12M) link to small data blocks exported from mart_q2_retention_q1_24 / mart_q4_ndr_t12m -- a full formula rebuild would require the row-level subscription table, which is out of this workbook's scope (that computation lives in SQL); this is stated on the tab.
A23: UnitEconomics | B23: Fully loaded CAC, revenue, COGS, GM% (driven by the GM-basis selector), ARPA, the 60-month survival-curve build, LTV, LTV:CAC, CAC payback, and the retention-adjusted payback on the full 60-month curve, by segment. Includes a GM-basis x lifetime-cap sensitivity grid.
A24: Scenarios | B24: A 12-month (May-24..Apr-25) formula-driven projection by segment, in three parallel Base/Bull/Bear blocks (no selector needed), plus a summary and a reconciliation block against the Python scenario engine (mart_s_03_scenario_summary).
A25: Strategies | B25: The WP23 retention-strategy table (6mo/12mo MRR delta, NDR delta, effort), linked to Assumptions where the impact is a simple formula, labelled 'from engine' where it comes from the Python simulation.
A26: Checks | B26: TRUE/FALSE reconciliation checks with a master ALL CHECKS PASS cell.
A28: Conventions
A29: Convention | B29: Meaning
A30: Blue font | B30: Hard-coded input (an assumption, or a value pasted from a SQL mart export on a Data_* tab).
A31: Black font | B31: A formula computed from other cells in this workbook.
A32: Green font | B32: A formula that links to a value on another tab (a cross-sheet reference / lookup).
A33: No hard-coded numbers in formulas | B33: Every formula points at an Assumptions/Data_* cell instead of embedding a number, except structural constants (12 months/year, 1).
A34: No macros / data tables / structured refs / dynamic-array-only functions / external links | B34: Only SUM, SUMIFS, SUMPRODUCT, INDEX/MATCH, IF, MIN/MAX, ROUND, AVERAGE, COUNTIFS, IFERROR, AND/OR and basic arithmetic are used, so the workbook opens and recalculates identically in Excel and Google Sheets.
A36: Data window
B37: Historical data: Jan-2023 .. Apr-2024 (16 months). As-of / snapshot date (M-01): 2024-04-30.
B38: Scenario projection: May-2024 .. Apr-2025 (12 months), seeded from the Apr-24 actuals.
B39: CAC / GM / ARPA windows: T6M = Nov-2023..Apr-2024 (base); T16M = Jan-2023..Apr-2024 (reference).
A41: How this links to the SQL pipeline
B42: Every Data_* tab is a verbatim export of one or more named marts/staging tables from db/platzi.duckdb
B43: (built by sql/run_pipeline.py from sql/staging -> sql/intermediate -> sql/marts, plus the Python
B44: scenario engine in sql/python_models/scenarios.py). This workbook does NOT recompute the SQL layer's
B45: own logic (retention definitions, the survival-curve tail-rate cascade, the monthly compartment
B46: simulation) -- it re-derives the assumptions/unit-economics/scenario CALCULATIONS from those exports
B47: using its own visible formulas, and cross-checks the results against the SQL/Python outputs on the
B48: Checks tab. Rerun sql/run_pipeline.py, then work/WP40_model/build_model.py, to refresh this file.
A50: Key caveats
B51: - GM% base case (all COGS allocated by MRR share) is uniform across segments BY CONSTRUCTION -- it cannot itself show any segment as more/less profitable than the company average (see UnitEconomics).
B52: - Retention-adjusted payback is now computed on the full extrapolated 60-month curve (this resolves the open issue in Docs/Plan_and_Index.md -- WP21's version only checked the observed 11-15 month horizon and always said 'never').
B53: - The Scenarios tab is a deliberately simplified single-bucket-per-segment model (it blends monthly/annual plan rates using the Apr-24 stock mix and ignores the B2C monthly->annual migration lever); it is reconciled against the full monthly-compartment Python engine within 3% on Apr-25 total MRR per scenario -- see the reconciliation block on the Scenarios tab for the exact gaps and why.
B54: - Q2 and Q4 are small linked data blocks from the SQL marts, not formula rebuilds (see Answers_Q1_Q4).
B55: - Enterprise and SMB unit-economics/survival figures rest on small samples (as few as ~58 new customers/6mo for Enterprise) -- treat them as directional, per WP20/21/22/31's repeated caveat.

Sheet Assumptions
A1: Assumptions
A2: Purpose: every input driver used anywhere in this workbook, with its ID, value, unit, source and note. Source = sql/marts/*.sql, sql/python_models/scenarios.py, or a WP results.md. Blue = hard-coded input pasted from the SQL layer or the brief; nothing on this tab is a formula.
A4: Key selectors & horizon dates
A5: Label | B5: Value | C5: Unit | D5: Source | E5: Note
A6: Scenario selector (informational -- Scenarios tab computes Base/Bull/Bear in parallel blocks, so no tab actually reads this cell) | B6: Base | C6: Base/Bull/Bear | D6: brief | E6: dropdown; kept for spec compliance / manual what-if reading
A7: GM basis selector | B7: T6M avg | C7: T6M avg/Apr-24 run-rate | D7: D-17 | E7: T6M avg 29.3%% (conservative, base) vs Apr-24 run-rate 40.9%% (upside sensitivity); drives GM% and LTV on UnitEconomics
A8: LTV horizon cap -- base | B8: 60 | C8: months | D8: A-18 | E8: proposed WP21; standard 5-yr SaaS planning horizon
A9: LTV horizon cap -- sensitivity | B9: 36 | C9: months | D9: A-18 | E9: conservative alternative reported alongside the 60mo base
A10: As-of / snapshot date (M-01) | B10: 45412 | C10: date | D10: M-01 | E10: April 2024 = snapshot at 2024-04-30
A11: T6M window start (month-end basis, for Data_MRR) | B11: 45260 | C11: date | D11: D-19/WP21 | E11: Nov-23..Apr-24
A12: T6M window start (month-start basis, for Data_Costs) | B12: 45231 | C12: date | D12: D-19/WP21 | E12: stg_marketing_spend/stg_support_costs use month-start dates
A13: T6M window end (month-start basis, for Data_Costs) | B13: 45383 | C13: date | D13: D-19/WP21
A14: T16M window start (month-end basis, for Data_MRR) | B14: 44957 | C14: date | D14: WP21 | E14: Jan-23..Apr-24
A15: T16M window start (month-start basis, for Data_Costs) | B15: 44927 | C15: date | D15: WP21
A16: Scenario horizon start (month 1 = May-24) | B16: 45443 | C16: date | D16: brief/WP31 | E16: 12-month projection starts the month after the as-of date
A17: Scenario horizon end (month 12 = Apr-25) | B17: 45777 | C17: date | D17: brief/WP31
A18: Benchmark: LTV:CAC | B18: 3 | C18: x | D18: brief/A2-012 | E18: SaaS rule of thumb, all segments
A19: Benchmark: CAC payback, B2C/SMB | B19: 12 | C19: months | D19: brief/A2-012
A20: Benchmark: CAC payback, Enterprise | B20: 18 | C20: months | D20: brief/A2-012 | E20: longer sales cycle allowance
A21: Tolerance: scenario reconciliation vs engine | B21: 0.03 | C21: relative % | D21: WP40 spec | E21: target <= 3% on Apr-25 total MRR per scenario
A22: Tolerance: scenario reconciliation, single segment | B22: 0.05 | C22: relative % | D22: Lead review (D-20) | E22: segment-level gaps are larger on small bases (e.g. SMB Bull stacks 3 levers); totals keep 3%
A23: Tolerance: sheet CAC/LTV vs mart_a2_12 | B23: 0.01 | C23: relative % | D23: WP40 spec
A24: QA target: Q1 total MRR Apr-24 | B24: 204709.09 | C24: USD | D24: mart_q1_mrr_apr24 | E24: sum of segments must tie to this
A25: QA target: Q3 total active subs Apr-24 | B25: 1941 | C25: customers | D25: mart_q3_active_subs_apr24
A27: Starting stock -- Apr-24 actuals (source: mart_q3_active_subs_apr24)
A28: Segment | B28: Plan type | C28: Active subs (Apr-24)
A29: B2C | B29: annual | C29: 692
A30: B2C | B30: monthly | C30: 844
A31: Enterprise | B31: annual | C31: 90
A32: Enterprise | B32: monthly | C32: 12
A33: SMB | B33: annual | C33: 190
A34: SMB | B34: monthly | C34: 113
A36: Starting MRR & customers -- Apr-24 actuals (link to Data_MRR)
A37: Segment | B37: Opening MRR (Apr-24) | C37: Opening customers (Apr-24)
A38: B2C | B38: =SUMIFS(Data_MRR!$H:$H,Data_MRR!$B:$B,"B2C",Data_MRR!$A:$A,Assumptions!$B$10) | C38: =SUMIFS(Data_MRR!$I:$I,Data_MRR!$B:$B,"B2C",Data_MRR!$A:$A,Assumptions!$B$10)
A39: SMB | B39: =SUMIFS(Data_MRR!$H:$H,Data_MRR!$B:$B,"SMB",Data_MRR!$A:$A,Assumptions!$B$10) | C39: =SUMIFS(Data_MRR!$I:$I,Data_MRR!$B:$B,"SMB",Data_MRR!$A:$A,Assumptions!$B$10)
A40: Enterprise | B40: =SUMIFS(Data_MRR!$H:$H,Data_MRR!$B:$B,"Enterprise",Data_MRR!$A:$A,Assumptions!$B$10) | C40: =SUMIFS(Data_MRR!$I:$I,Data_MRR!$B:$B,"Enterprise",Data_MRR!$A:$A,Assumptions!$B$10)
A42: Survival-curve tail parameters (Proposed A-23; source: mart_a2_11_lifetime.sql)
A43: Segment | B43: Reliable horizon k_rel (months) | C43: Dollar tail decay/mo | D43: Logo tail churn/mo
A44: B2C | B44: 15 | C44: 0.049429713 | D44: 0.035159717
A45: SMB | B45: 14 | C45: 0.012226731 | D45: 0.012226731
A46: Enterprise | B46: 11 | C46: 0.018322967 | D46: 0.014054199
A47: A-23 (new, proposed): the tail decay/churn rate itself (computed in SQL by the cascading last3->last6->full_range fallback logic, A-16/A-17) is exposed here as a plain input so the 60-month curve can be rebuilt with formulas on UnitEconomics, per the WP40 spec ('build the 60-row monthly curve on the tab itself... using the tail churn from Assumptions'). The cascading SELECTION of which window to use is not re-derived in the Sheet.
A49: Scenario engine drivers -- T6M calibration (source: mart_s_01_drivers / WP31 sheet_inputs.csv S-002..S-037)
A50: Driver | B50: B2C | C50: SMB | D50: Enterprise | E50: Unit | F50: Source IDs (B2C/SMB/Ent) | G50: Note
A51: new_customers_per_month_avg | B51: =INDEX(Assumptions!$C$305:$C$362,MATCH("S-002",Assumptions!$A$305:$A$362,0)) | C51: =INDEX(Assumptions!$C$305:$C$362,MATCH("S-026",Assumptions!$A$305:$A$362,0)) | D51: =INDEX(Assumptions!$C$305:$C$362,MATCH("S-014",Assumptions!$A$305:$A$362,0)) | E51: customers/month | F51: S-002/S-026/S-014 | G51: T6M average new paying customers
A52: new_customers_trend_slope | B52: =INDEX(Assumptions!$C$305:$C$362,MATCH("S-003",Assumptions!$A$305:$A$362,0)) | C52: =INDEX(Assumptions!$C$305:$C$362,MATCH("S-027",Assumptions!$A$305:$A$362,0)) | D52: =INDEX(Assumptions!$C$305:$C$362,MATCH("S-015",Assumptions!$A$305:$A$362,0)) | E52: customers/month per month | F52: S-003/S-027/S-015 | G52: OLS trend over the T6M window; used in Bull only, floored at the flat average
A53: arpa_new_customer_monthly_plan | B53: =INDEX(Assumptions!$C$305:$C$362,MATCH("S-009",Assumptions!$A$305:$A$362,0)) | C53: =INDEX(Assumptions!$C$305:$C$362,MATCH("S-033",Assumptions!$A$305:$A$362,0)) | D53: =INDEX(Assumptions!$C$305:$C$362,MATCH("S-021",Assumptions!$A$305:$A$362,0)) | E53: $/month | F53: S-009/S-033/S-021 | G53: avg mrr of new monthly-plan subs, T6M
A54: arpa_new_customer_annual_plan | B54: =INDEX(Assumptions!$C$305:$C$362,MATCH("S-004",Assumptions!$A$305:$A$362,0)) | C54: =INDEX(Assumptions!$C$305:$C$362,MATCH("S-028",Assumptions!$A$305:$A$362,0)) | D54: =INDEX(Assumptions!$C$305:$C$362,MATCH("S-016",Assumptions!$A$305:$A$362,0)) | E54: $/month | F54: S-004/S-028/S-016 | G54: avg mrr of new annual-plan subs, T6M
A55: plan_mix_share_monthly (of new custs) | B55: =INDEX(Assumptions!$C$305:$C$362,MATCH("S-013",Assumptions!$A$305:$A$362,0)) | C55: =INDEX(Assumptions!$C$305:$C$362,MATCH("S-037",Assumptions!$A$305:$A$362,0)) | D55: =INDEX(Assumptions!$C$305:$C$362,MATCH("S-025",Assumptions!$A$305:$A$362,0)) | E55: fraction | F55: S-013/S-037/S-025 | G55: T6M share of new customers on the monthly plan
A56: plan_mix_share_annual (of new custs) | B56: =INDEX(Assumptions!$C$305:$C$362,MATCH("S-008",Assumptions!$A$305:$A$362,0)) | C56: =INDEX(Assumptions!$C$305:$C$362,MATCH("S-032",Assumptions!$A$305:$A$362,0)) | D56: =INDEX(Assumptions!$C$305:$C$362,MATCH("S-020",Assumptions!$A$305:$A$362,0)) | E56: fraction | F56: S-008/S-032/S-020 | G56: T6M share of new customers on the annual plan
A57: churn_rate_monthly_plan | B57: =INDEX(Assumptions!$C$305:$C$362,MATCH("S-010",Assumptions!$A$305:$A$362,0)) | C57: =INDEX(Assumptions!$C$305:$C$362,MATCH("S-034",Assumptions!$A$305:$A$362,0)) | D57: =INDEX(Assumptions!$C$305:$C$362,MATCH("S-022",Assumptions!$A$305:$A$362,0)) | E57: fraction/month | F57: S-010/S-034/S-022 | G57: renewal-basis, T6M
A58: churn_rate_annual_plan (monthly-equiv, A-19c) | B58: =INDEX(Assumptions!$C$305:$C$362,MATCH("S-005",Assumptions!$A$305:$A$362,0)) | C58: =INDEX(Assumptions!$C$305:$C$362,MATCH("S-029",Assumptions!$A$305:$A$362,0)) | D58: =INDEX(Assumptions!$C$305:$C$362,MATCH("S-017",Assumptions!$A$305:$A$362,0)) | E58: fraction/month | F58: S-005/S-029/S-017 | G58: annual rate converted via 1-(1-r)^(1/12)
A59: expansion_rate_monthly (B2B; B2C=0 by construction) | B59: =INDEX(Assumptions!$C$305:$C$362,MATCH("S-012",Assumptions!$A$305:$A$362,0)) | C59: =INDEX(Assumptions!$C$305:$C$362,MATCH("S-036",Assumptions!$A$305:$A$362,0)) | D59: =INDEX(Assumptions!$C$305:$C$362,MATCH("S-024",Assumptions!$A$305:$A$362,0)) | E59: fraction/mo of retained MRR | F59: S-012/S-036/S-024 | G59: identical for monthly/annual buckets in the source decomposition
A60: contraction_rate_monthly (B2B; B2C=0 by construction) | B60: =INDEX(Assumptions!$C$305:$C$362,MATCH("S-011",Assumptions!$A$305:$A$362,0)) | C60: =INDEX(Assumptions!$C$305:$C$362,MATCH("S-035",Assumptions!$A$305:$A$362,0)) | D60: =INDEX(Assumptions!$C$305:$C$362,MATCH("S-023",Assumptions!$A$305:$A$362,0)) | E60: fraction/mo of retained MRR | F60: S-011/S-035/S-023 | G60: identical for monthly/annual buckets in the source decomposition
A62: Bear scenario stress constants (Proposed A-19; source: WP31 sheet_inputs.csv)
A63: Constant | B63: Value | C63: Unit | D63: Source ID | E63: Note
A64: Acquisition relative decline (all segments) | B64: =INDEX(Assumptions!$C$305:$C$362,MATCH("S-038",Assumptions!$A$305:$A$362,0)) | C64: relative % | D64: S-038 | E64: ~1.5x the worst observed single-month new-customer decline, sustained 12mo
A65: Churn relative increase (all segments) | B65: =INDEX(Assumptions!$C$305:$C$362,MATCH("S-039",Assumptions!$A$305:$A$362,0)) | C65: relative % | D65: S-039 | E65: largest observed positive MoM deviation in B2C-monthly churn
A66: SMB expansion multiplier | B66: =INDEX(Assumptions!$C$305:$C$362,MATCH("S-041",Assumptions!$A$305:$A$362,0)) | C66: multiplier | D66: S-041 | E66: brief: bear = expansion halved
A67: Enterprise expansion multiplier | B67: =INDEX(Assumptions!$C$305:$C$362,MATCH("S-040",Assumptions!$A$305:$A$362,0)) | C67: multiplier | D67: S-040 | E67: brief: bear = expansion halved
A69: Bull scenario levers -- WP23 strategies at base case (Proposed A-20/A-21/A-22; source: WP31 sheet_inputs.csv)
A70: Lever | B70: Value | C70: Unit | D70: Source ID | E70: Note
A71: Strategy-1 churn save rate (monthly-plan churn only, all segments) | B71: =INDEX(Assumptions!$C$305:$C$362,MATCH("S-043",Assumptions!$A$305:$A$362,0)) | C71: fraction saved | D71: S-043 | E71: base case (low 10% / high 30%)
A72: Strategy-2 B2C monthly->annual migration rate | B72: =INDEX(Assumptions!$C$305:$C$362,MATCH("S-044",Assumptions!$A$305:$A$362,0)) | C72: fraction/month | D72: S-044 | E72: NOT modelled in the simplified Scenarios engine below (see gap note); shown here for completeness / used on the Strategies tab
A73: Strategy-3 SMB expansion uplift | B73: =INDEX(Assumptions!$C$305:$C$362,MATCH("S-046",Assumptions!$A$305:$A$362,0)) | C73: relative % | D73: S-046 | E73: base case (low 20% / high 60%)
A74: Strategy-3 Enterprise contraction reduction | B74: =INDEX(Assumptions!$C$305:$C$362,MATCH("S-045",Assumptions!$A$305:$A$362,0)) | C74: relative % | D74: S-045 | E74: base case (low 30% / high 70%)
A76: Strategy-1 illustrative check inputs (source: mart_a1_06_may24_churn_risk, D-16 risk tiers)
A77: May-24 High+Medium risk MRR (flagged) | B77: 5494.61 | C77: USD | D77: mart_a1_06_may24_churn_risk | E77: sum(mrr) where risk_tier in (High, Medium)
A78: ...of which expected to churn (mrr_at_risk) | B78: 3812.3574 | C78: USD | D78: mart_a1_06_may24_churn_risk | E78: sum(mrr_at_risk) where risk_tier in (High, Medium)
A200: Full assumptions register -- traceability (WP21 sheet_inputs.csv, A2-001..A2-099)
A201: id | B201: name | C201: value | D201: unit | E201: source | F201: note
A202: A2-001 | B202: D-06: CAC denominator | C202: new paying customers (users.csv signups) | D202: definition | E202: D-06 (approved) | F202: marketing new_users_acquired reported only as a funnel metric, not the CAC denominator
A203: A2-002 | B203: D-05: G&A allocation formula | C203: marketing / (marketing + support costs) x total G&A | D203: formula | E203: D-05 (proposed) | F203: support costs = CS Salaries + Infrastructure + Content Production (excl. G&A itself)
A204: A2-003 | B204: D-05: G&A segment split (base) | C204: by segment share of marketing spend | D204: definition | E204: D-05 (proposed) | F204: sensitivity: by share of new customers
A205: A2-004 | B205: GM allocation (base, revised) | C205: all COGS (CS Salaries + Infrastructure + Content Production) by MRR share | D205: definition | E205: results.md WP21 (lead-analyst review) | F205: neutral default with no cost-driver data; forces uniform GM% across segments by construction
A206: A2-005 | B206: GM allocation (downside sensitivity) | C206: CS Salaries & Infrastructure by active-customer share; Content by MRR share | D206: definition | E206: results.md WP21 | F206: was the base case in the prior draft (-37% B2C GM%); demoted to sensitivity per review
A207: A2-006 | B207: Proposed A-15: survival curve reliability threshold | C207: 20 | D207: min cohort exposure n per k | E207: mart_a2_11_lifetime.sql | F207: k-points with exposed_n below this are dropped as unreliable/too-censored
A208: A2-007 | B208: Proposed A-16: dollar curve tail fallback | C208: use logo tail churn | D208: rule | E208: mart_a2_11_lifetime.sql | F208: applied when no window shows net dollar decay (net expansion in the tail)
A209: A2-008 | B209: Proposed A-17: dollar curve tail floor | C209: dollar decay >= logo tail churn | D209: rule | E209: mart_a2_11_lifetime.sql | F209: prevents implausible multi-decade LTV when dollar-tail decay is near zero on a small sample (SMB)
A210: A2-009 | B210: Proposed A-18: LTV horizon cap | C210: 60 months (base) | D210: months | E210: mart_a2_11_lifetime.sql | F210: sensitivity 36 months; uncapped reference also reported
A211: A2-010 | B211: Tail churn estimation window | C211: cascading last3 -> last6 -> full_range average of period-over-period ratios | D211: method | E211: mart_a2_11_lifetime.sql
A212: A2-011 | B212: ARPA / GM% base window | C212: T6M average (Nov-23..Apr-24) | D212: period | E212: mart_a2_08/09 | F212: T16M and Apr-24 snapshot also reported
A213: A2-012 | B213: Enterprise payback benchmark | C213: 18 | D213: months | E213: SaaS benchmark (brief) | F213: vs 12 months for B2C/SMB; LTV:CAC benchmark = 3.0x for all segments
A214: A2-013 | B214: Enterprise: marketing spend (T16M) | C214: 481235.59 | D214: USD | E214: mart_a2_02/03
A215: A2-014 | B215: Enterprise: new signups per marketing (T16M) | C215: 82 | D215: signups | E215: marketing_spend.csv
A216: A2-015 | B216: Enterprise: new paying customers (T16M, D-06 base) | C216: 109 | D216: customers | E216: users.csv / mart_a2_01
A217: A2-016 | B217: Enterprise: cost per signup (T16M) | C217: 5868.73 | D217: USD/signup | E217: mart_a2_03
A218: A2-017 | B218: Enterprise: signup->paid conversion (T16M) | C218: 1.3293 | D218: ratio | E218: mart_a2_03 | F218: Enterprise > 100%: users.csv (109) > marketing signups (82) -- D-11 caveat
A219: A2-018 | B219: B2C: marketing spend (T16M) | C219: 789794.31 | D219: USD | E219: mart_a2_02/03
A220: A2-019 | B220: B2C: new signups per marketing (T16M) | C220: 21573 | D220: signups | E220: marketing_spend.csv
A221: A2-020 | B221: B2C: new paying customers (T16M, D-06 base) | C221: 2225 | D221: customers | E221: users.csv / mart_a2_01
A222: A2-021 | B222: B2C: cost per signup (T16M) | C222: 36.61 | D222: USD/signup | E222: mart_a2_03
A223: A2-022 | B223: B2C: signup->paid conversion (T16M) | C223: 0.1031 | D223: ratio | E223: mart_a2_03 | F223: Enterprise > 100%: users.csv (109) > marketing signups (82) -- D-11 caveat
A224: A2-023 | B224: SMB: marketing spend (T16M) | C224: 253809.03 | D224: USD | E224: mart_a2_02/03
A225: A2-024 | B225: SMB: new signups per marketing (T16M) | C225: 695 | D225: signups | E225: marketing_spend.csv
A226: A2-025 | B226: SMB: new paying customers (T16M, D-06 base) | C226: 361 | D226: customers | E226: users.csv / mart_a2_01
A227: A2-026 | B227: SMB: cost per signup (T16M) | C227: 365.19 | D227: USD/signup | E227: mart_a2_03
A228: A2-027 | B228: SMB: signup->paid conversion (T16M) | C228: 0.5194 | D228: ratio | E228: mart_a2_03 | F228: Enterprise > 100%: users.csv (109) > marketing signups (82) -- D-11 caveat
A229: A2-028 | B229: B2C/Organic: cost per signup (T16M) | C229: 14.47 | D229: USD/signup | E229: mart_a2_04
...

Sheet Data_MRR
A1: Data_MRR
A2: Source: mart_mrr_bridge.sql (verbatim export). Monthly MRR bridge by segment, Jan-23..Apr-24: opening -> +new +expansion -contraction -churn -> closing, plus active customers. Blank expansion/contraction/churn cells = $0 (no movement of that type that month) -- treated as 0 in all downstream formulas.
A4: month_end | B4: segment | C4: opening_mrr | D4: new_mrr | E4: expansion_mrr | F4: contraction_mrr | G4: churn_mrr | H4: closing_mrr | I4: active_customers | J4: bridge_check (opening+new+exp-contr-churn=closing)
A5: 44957 | B5: B2B | C5: 0 | D5: 3195.6 | H5: 3195.6 | I5: 11 | J5: =ROUND(IFERROR(C5,0)+IFERROR(D5,0)+IFERROR(E5,0)-IFERROR(F5,0)-IFERROR(G5,0)-IFERROR(H5,0),2)=0
A6: 44985 | B6: B2B | C6: 3195.6 | D6: 4260.12 | E6: 54.51 | F6: 39.28 | H6: 7470.95 | I6: 28 | J6: =ROUND(IFERROR(C6,0)+IFERROR(D6,0)+IFERROR(E6,0)-IFERROR(F6,0)-IFERROR(G6,0)-IFERROR(H6,0),2)=0
A7: 45016 | B7: B2B | C7: 7470.95 | D7: 7130.44 | H7: 14601.39 | I7: 49 | J7: =ROUND(IFERROR(C7,0)+IFERROR(D7,0)+IFERROR(E7,0)-IFERROR(F7,0)-IFERROR(G7,0)-IFERROR(H7,0),2)=0
A8: 45046 | B8: B2B | C8: 14601.39 | D8: 5855.68 | E8: 66.39 | F8: 32.92 | G8: 1189 | H8: 19301.54 | I8: 64 | J8: =ROUND(IFERROR(C8,0)+IFERROR(D8,0)+IFERROR(E8,0)-IFERROR(F8,0)-IFERROR(G8,0)-IFERROR(H8,0),2)=0
A9: 45077 | B9: B2B | C9: 19301.54 | D9: 9365.04 | E9: 158.72 | G9: 231.72 | H9: 28593.58 | I9: 91 | J9: =ROUND(IFERROR(C9,0)+IFERROR(D9,0)+IFERROR(E9,0)-IFERROR(F9,0)-IFERROR(G9,0)-IFERROR(H9,0),2)=0
A10: 45107 | B10: B2B | C10: 28593.58 | D10: 7561.28 | E10: 127.71 | F10: 47.5 | G10: 2378 | H10: 33857.07 | I10: 109 | J10: =ROUND(IFERROR(C10,0)+IFERROR(D10,0)+IFERROR(E10,0)-IFERROR(F10,0)-IFERROR(G10,0)-IFERROR(H10,0),2)=0
A11: 45138 | B11: B2B | C11: 33857.07 | D11: 9561.36 | E11: 106.15 | F11: 220.44 | G11: 396.93 | H11: 42907.21 | I11: 135 | J11: =ROUND(IFERROR(C11,0)+IFERROR(D11,0)+IFERROR(E11,0)-IFERROR(F11,0)-IFERROR(G11,0)-IFERROR(H11,0),2)=0
A12: 45169 | B12: B2B | C12: 42907.21 | D12: 7978.2 | E12: 394.11 | F12: 83.58 | G12: 995 | H12: 50200.94 | I12: 156 | J12: =ROUND(IFERROR(C12,0)+IFERROR(D12,0)+IFERROR(E12,0)-IFERROR(F12,0)-IFERROR(G12,0)-IFERROR(H12,0),2)=0
A13: 45199 | B13: B2B | C13: 50200.94 | D13: 9780.8 | E13: 694.3 | F13: 64.87 | G13: 325.85 | H13: 60285.32 | I13: 184 | J13: =ROUND(IFERROR(C13,0)+IFERROR(D13,0)+IFERROR(E13,0)-IFERROR(F13,0)-IFERROR(G13,0)-IFERROR(H13,0),2)=0
A14: 45230 | B14: B2B | C14: 60285.32 | D14: 9679.96 | E14: 247.75 | F14: 75.2 | G14: 1297.78 | H14: 68840.05 | I14: 207 | J14: =ROUND(IFERROR(C14,0)+IFERROR(D14,0)+IFERROR(E14,0)-IFERROR(F14,0)-IFERROR(G14,0)-IFERROR(H14,0),2)=0
A15: 45260 | B15: B2B | C15: 68840.05 | D15: 11991.12 | E15: 323.42 | F15: 32.51 | G15: 619.75 | H15: 80502.33 | I15: 237 | J15: =ROUND(IFERROR(C15,0)+IFERROR(D15,0)+IFERROR(E15,0)-IFERROR(F15,0)-IFERROR(G15,0)-IFERROR(H15,0),2)=0
A16: 45291 | B16: B2B | C16: 80502.33 | D16: 12984.96 | E16: 490.81 | F16: 39.06 | G16: 3422.57 | H16: 90516.47 | I16: 261 | J16: =ROUND(IFERROR(C16,0)+IFERROR(D16,0)+IFERROR(E16,0)-IFERROR(F16,0)-IFERROR(G16,0)-IFERROR(H16,0),2)=0
A17: 45322 | B17: B2B | C17: 90516.47 | D17: 13236.88 | E17: 562.92 | F17: 241.39 | G17: 1459.44 | H17: 102615.44 | I17: 294 | J17: =ROUND(IFERROR(C17,0)+IFERROR(D17,0)+IFERROR(E17,0)-IFERROR(F17,0)-IFERROR(G17,0)-IFERROR(H17,0),2)=0
A18: 45351 | B18: B2B | C18: 102615.44 | D18: 14049.48 | E18: 678.69 | F18: 296.23 | G18: 2142.42 | H18: 114904.96 | I18: 331 | J18: =ROUND(IFERROR(C18,0)+IFERROR(D18,0)+IFERROR(E18,0)-IFERROR(F18,0)-IFERROR(G18,0)-IFERROR(H18,0),2)=0
A19: 45382 | B19: B2B | C19: 114904.96 | D19: 14627.56 | E19: 390.39 | F19: 50.82 | G19: 1936.28 | H19: 127935.81 | I19: 368 | J19: =ROUND(IFERROR(C19,0)+IFERROR(D19,0)+IFERROR(E19,0)-IFERROR(F19,0)-IFERROR(G19,0)-IFERROR(H19,0),2)=0
A20: 45412 | B20: B2B | C20: 127935.81 | D20: 13902.24 | E20: 697.93 | F20: 112 | G20: 2079.89 | H20: 140344.09 | I20: 405 | J20: =ROUND(IFERROR(C20,0)+IFERROR(D20,0)+IFERROR(E20,0)-IFERROR(F20,0)-IFERROR(G20,0)-IFERROR(H20,0),2)=0
A21: 44957 | B21: B2C | C21: 0 | D21: 3969 | H21: 3969 | I21: 90 | J21: =ROUND(IFERROR(C21,0)+IFERROR(D21,0)+IFERROR(E21,0)-IFERROR(F21,0)-IFERROR(G21,0)-IFERROR(H21,0),2)=0
A22: 44985 | B22: B2C | C22: 3969 | D22: 3739.75 | G22: 392 | H22: 7316.75 | I22: 167 | J22: =ROUND(IFERROR(C22,0)+IFERROR(D22,0)+IFERROR(E22,0)-IFERROR(F22,0)-IFERROR(G22,0)-IFERROR(H22,0),2)=0
A23: 45016 | B23: B2C | C23: 7316.75 | D23: 4588.5 | G23: 343 | H23: 11562.25 | I23: 262 | J23: =ROUND(IFERROR(C23,0)+IFERROR(D23,0)+IFERROR(E23,0)-IFERROR(F23,0)-IFERROR(G23,0)-IFERROR(H23,0),2)=0
A24: 45046 | B24: B2C | C24: 11562.25 | D24: 4740.75 | G24: 833 | H24: 15470 | I24: 353 | J24: =ROUND(IFERROR(C24,0)+IFERROR(D24,0)+IFERROR(E24,0)-IFERROR(F24,0)-IFERROR(G24,0)-IFERROR(H24,0),2)=0
A25: 45077 | B25: B2C | C25: 15470 | D25: 4611.25 | G25: 1176 | H25: 18905.25 | I25: 435 | J25: =ROUND(IFERROR(C25,0)+IFERROR(D25,0)+IFERROR(E25,0)-IFERROR(F25,0)-IFERROR(G25,0)-IFERROR(H25,0),2)=0
A26: 45107 | B26: B2C | C26: 18905.25 | D26: 5544 | G26: 1617 | H26: 22832.25 | I26: 528 | J26: =ROUND(IFERROR(C26,0)+IFERROR(D26,0)+IFERROR(E26,0)-IFERROR(F26,0)-IFERROR(G26,0)-IFERROR(H26,0),2)=0
A27: 45138 | B27: B2C | C27: 22832.25 | D27: 5372.5 | G27: 1078 | H27: 27126.75 | I27: 624 | J27: =ROUND(IFERROR(C27,0)+IFERROR(D27,0)+IFERROR(E27,0)-IFERROR(F27,0)-IFERROR(G27,0)-IFERROR(H27,0),2)=0
A28: 45169 | B28: B2C | C28: 27126.75 | D28: 5836.25 | G28: 1911 | H28: 31052 | I28: 716 | J28: =ROUND(IFERROR(C28,0)+IFERROR(D28,0)+IFERROR(E28,0)-IFERROR(F28,0)-IFERROR(G28,0)-IFERROR(H28,0),2)=0
A29: 45199 | B29: B2C | C29: 31052 | D29: 6443.5 | G29: 2450 | H29: 35045.5 | I29: 811 | J29: =ROUND(IFERROR(C29,0)+IFERROR(D29,0)+IFERROR(E29,0)-IFERROR(F29,0)-IFERROR(G29,0)-IFERROR(H29,0),2)=0
A30: 45230 | B30: B2C | C30: 35045.5 | D30: 7071.75 | G30: 2744 | H30: 39373.25 | I30: 917 | J30: =ROUND(IFERROR(C30,0)+IFERROR(D30,0)+IFERROR(E30,0)-IFERROR(F30,0)-IFERROR(G30,0)-IFERROR(H30,0),2)=0
A31: 45260 | B31: B2C | C31: 39373.25 | D31: 6676.25 | G31: 2842 | H31: 43207.5 | I31: 1011 | J31: =ROUND(IFERROR(C31,0)+IFERROR(D31,0)+IFERROR(E31,0)-IFERROR(F31,0)-IFERROR(G31,0)-IFERROR(H31,0),2)=0
A32: 45291 | B32: B2C | C32: 43207.5 | D32: 7103.25 | G32: 3381 | H32: 46929.75 | I32: 1104 | J32: =ROUND(IFERROR(C32,0)+IFERROR(D32,0)+IFERROR(E32,0)-IFERROR(F32,0)-IFERROR(G32,0)-IFERROR(H32,0),2)=0
A33: 45322 | B33: B2C | C33: 46929.75 | D33: 7269.5 | G33: 3724 | H33: 50475.25 | I33: 1195 | J33: =ROUND(IFERROR(C33,0)+IFERROR(D33,0)+IFERROR(E33,0)-IFERROR(F33,0)-IFERROR(G33,0)-IFERROR(H33,0),2)=0
... A36: 45412 | B36: B2C | C36: 59468.5 | D36: 8800.75 | G36: 3904.25 | H36: 64365 | I36: 1536 | J36: =ROUND(IFERROR(C36,0)+IFERROR(D36,0)+IFERROR(E36,0)-IFERROR(F36,0)-IFERROR(G36,0)-IFERROR(H36,0),2)=0
A37: 44957 | B37: Enterprise | C37: 0 | D37: 1650 | H37: 1650 | I37: 2 | J37: =ROUND(IFERROR(C37,0)+IFERROR(D37,0)+IFERROR(E37,0)-IFERROR(F37,0)-IFERROR(G37,0)-IFERROR(H37,0),2)=0
A38: 44985 | B38: Enterprise | C38: 1650 | D38: 1815 | H38: 3465 | I38: 4 | J38: =ROUND(IFERROR(C38,0)+IFERROR(D38,0)+IFERROR(E38,0)-IFERROR(F38,0)-IFERROR(G38,0)-IFERROR(H38,0),2)=0
A39: 45016 | B39: Enterprise | C39: 3465 | D39: 4290 | H39: 7755 | I39: 9 | J39: =ROUND(IFERROR(C39,0)+IFERROR(D39,0)+IFERROR(E39,0)-IFERROR(F39,0)-IFERROR(G39,0)-IFERROR(H39,0),2)=0
A40: 45046 | B40: Enterprise | C40: 7755 | D40: 3465 | G40: 990 | H40: 10230 | I40: 12 | J40: =ROUND(IFERROR(C40,0)+IFERROR(D40,0)+IFERROR(E40,0)-IFERROR(F40,0)-IFERROR(G40,0)-IFERROR(H40,0),2)=0
A41: 45077 | B41: Enterprise | C41: 10230 | D41: 5775 | H41: 16005 | I41: 19 | J41: =ROUND(IFERROR(C41,0)+IFERROR(D41,0)+IFERROR(E41,0)-IFERROR(F41,0)-IFERROR(G41,0)-IFERROR(H41,0),2)=0
A42: 45107 | B42: Enterprise | C42: 16005 | D42: 4620 | G42: 1980 | H42: 18645 | I42: 22 | J42: =ROUND(IFERROR(C42,0)+IFERROR(D42,0)+IFERROR(E42,0)-IFERROR(F42,0)-IFERROR(G42,0)-IFERROR(H42,0),2)=0
A43: 45138 | B43: Enterprise | C43: 18645 | D43: 5775 | E43: 59.82 | F43: 194.74 | H43: 24285.08 | I43: 29 | J43: =ROUND(IFERROR(C43,0)+IFERROR(D43,0)+IFERROR(E43,0)-IFERROR(F43,0)-IFERROR(G43,0)-IFERROR(H43,0),2)=0
A44: 45169 | B44: Enterprise | C44: 24285.08 | D44: 4290 | E44: 81.57 | H44: 28656.65 | I44: 34 | J44: =ROUND(IFERROR(C44,0)+IFERROR(D44,0)+IFERROR(E44,0)-IFERROR(F44,0)-IFERROR(G44,0)-IFERROR(H44,0),2)=0
A45: 45199 | B45: Enterprise | C45: 28656.65 | D45: 5940 | E45: 232.84 | H45: 34829.49 | I45: 41 | J45: =ROUND(IFERROR(C45,0)+IFERROR(D45,0)+IFERROR(E45,0)-IFERROR(F45,0)-IFERROR(G45,0)-IFERROR(H45,0),2)=0
A46: 45230 | B46: Enterprise | C46: 34829.49 | D46: 5940 | E46: 70.93 | H46: 40840.42 | I46: 48 | J46: =ROUND(IFERROR(C46,0)+IFERROR(D46,0)+IFERROR(E46,0)-IFERROR(F46,0)-IFERROR(G46,0)-IFERROR(H46,0),2)=0
A47: 45260 | B47: Enterprise | C47: 40840.42 | D47: 7755 | H47: 48595.42 | I47: 57 | J47: =ROUND(IFERROR(C47,0)+IFERROR(D47,0)+IFERROR(E47,0)-IFERROR(F47,0)-IFERROR(G47,0)-IFERROR(H47,0),2)=0
A48: 45291 | B48: Enterprise | C48: 48595.42 | D48: 8250 | G48: 1071.57 | H48: 55773.85 | I48: 66 | J48: =ROUND(IFERROR(C48,0)+IFERROR(D48,0)+IFERROR(E48,0)-IFERROR(F48,0)-IFERROR(G48,0)-IFERROR(H48,0),2)=0
A49: 45322 | B49: Enterprise | C49: 55773.85 | D49: 7755 | E49: 121.3 | F49: 147.7 | H49: 63502.45 | I49: 75 | J49: =ROUND(IFERROR(C49,0)+IFERROR(D49,0)+IFERROR(E49,0)-IFERROR(F49,0)-IFERROR(G49,0)-IFERROR(H49,0),2)=0
A50: 45351 | B50: Enterprise | C50: 63502.45 | D50: 8415 | E50: 225.21 | F50: 127.64 | G50: 990 | H50: 71025.02 | I50: 84 | J50: =ROUND(IFERROR(C50,0)+IFERROR(D50,0)+IFERROR(E50,0)-IFERROR(F50,0)-IFERROR(G50,0)-IFERROR(H50,0),2)=0
A51: 45382 | B51: Enterprise | C51: 71025.02 | D51: 8745 | G51: 825 | H51: 78945.02 | I51: 93 | J51: =ROUND(IFERROR(C51,0)+IFERROR(D51,0)+IFERROR(E51,0)-IFERROR(F51,0)-IFERROR(G51,0)-IFERROR(H51,0),2)=0
A52: 45412 | B52: Enterprise | C52: 78945.02 | D52: 8415 | E52: 164.52 | G52: 1049.82 | H52: 86474.72 | I52: 102 | J52: =ROUND(IFERROR(C52,0)+IFERROR(D52,0)+IFERROR(E52,0)-IFERROR(F52,0)-IFERROR(G52,0)-IFERROR(H52,0),2)=0
A53: 44957 | B53: SMB | C53: 0 | D53: 1545.6 | H53: 1545.6 | I53: 9 | J53: =ROUND(IFERROR(C53,0)+IFERROR(D53,0)+IFERROR(E53,0)-IFERROR(F53,0)-IFERROR(G53,0)-IFERROR(H53,0),2)=0
A54: 44985 | B54: SMB | C54: 1545.6 | D54: 2445.12 | E54: 54.51 | F54: 39.28 | H54: 4005.95 | I54: 24 | J54: =ROUND(IFERROR(C54,0)+IFERROR(D54,0)+IFERROR(E54,0)-IFERROR(F54,0)-IFERROR(G54,0)-IFERROR(H54,0),2)=0
A55: 45016 | B55: SMB | C55: 4005.95 | D55: 2840.44 | H55: 6846.39 | I55: 40 | J55: =ROUND(IFERROR(C55,0)+IFERROR(D55,0)+IFERROR(E55,0)-IFERROR(F55,0)-IFERROR(G55,0)-IFERROR(H55,0),2)=0
A56: 45046 | B56: SMB | C56: 6846.39 | D56: 2390.68 | E56: 66.39 | F56: 32.92 | G56: 199 | H56: 9071.54 | I56: 52 | J56: =ROUND(IFERROR(C56,0)+IFERROR(D56,0)+IFERROR(E56,0)-IFERROR(F56,0)-IFERROR(G56,0)-IFERROR(H56,0),2)=0
A57: 45077 | B57: SMB | C57: 9071.54 | D57: 3590.04 | E57: 158.72 | G57: 231.72 | H57: 12588.58 | I57: 72 | J57: =ROUND(IFERROR(C57,0)+IFERROR(D57,0)+IFERROR(E57,0)-IFERROR(F57,0)-IFERROR(G57,0)-IFERROR(H57,0),2)=0
A58: 45107 | B58: SMB | C58: 12588.58 | D58: 2941.28 | E58: 127.71 | F58: 47.5 | G58: 398 | H58: 15212.07 | I58: 87 | J58: =ROUND(IFERROR(C58,0)+IFERROR(D58,0)+IFERROR(E58,0)-IFERROR(F58,0)-IFERROR(G58,0)-IFERROR(H58,0),2)=0
A59: 45138 | B59: SMB | C59: 15212.07 | D59: 3786.36 | E59: 46.33 | F59: 25.7 | G59: 396.93 | H59: 18622.13 | I59: 106 | J59: =ROUND(IFERROR(C59,0)+IFERROR(D59,0)+IFERROR(E59,0)-IFERROR(F59,0)-IFERROR(G59,0)-IFERROR(H59,0),2)=0
A60: 45169 | B60: SMB | C60: 18622.13 | D60: 3688.2 | E60: 312.54 | F60: 83.58 | G60: 995 | H60: 21544.29 | I60: 122 | J60: =ROUND(IFERROR(C60,0)+IFERROR(D60,0)+IFERROR(E60,0)-IFERROR(F60,0)-IFERROR(G60,0)-IFERROR(H60,0),2)=0
A61: 45199 | B61: SMB | C61: 21544.29 | D61: 3840.8 | E61: 461.46 | F61: 64.87 | G61: 325.85 | H61: 25455.83 | I61: 143 | J61: =ROUND(IFERROR(C61,0)+IFERROR(D61,0)+IFERROR(E61,0)-IFERROR(F61,0)-IFERROR(G61,0)-IFERROR(H61,0),2)=0
A62: 45230 | B62: SMB | C62: 25455.83 | D62: 3739.96 | E62: 176.82 | F62: 75.2 | G62: 1297.78 | H62: 27999.63 | I62: 159 | J62: =ROUND(IFERROR(C62,0)+IFERROR(D62,0)+IFERROR(E62,0)-IFERROR(F62,0)-IFERROR(G62,0)-IFERROR(H62,0),2)=0
A63: 45260 | B63: SMB | C63: 27999.63 | D63: 4236.12 | E63: 323.42 | F63: 32.51 | G63: 619.75 | H63: 31906.91 | I63: 180 | J63: =ROUND(IFERROR(C63,0)+IFERROR(D63,0)+IFERROR(E63,0)-IFERROR(F63,0)-IFERROR(G63,0)-IFERROR(H63,0),2)=0
A64: 45291 | B64: SMB | C64: 31906.91 | D64: 4734.96 | E64: 490.81 | F64: 39.06 | G64: 2351 | H64: 34742.62 | I64: 195 | J64: =ROUND(IFERROR(C64,0)+IFERROR(D64,0)+IFERROR(E64,0)-IFERROR(F64,0)-IFERROR(G64,0)-IFERROR(H64,0),2)=0
A65: 45322 | B65: SMB | C65: 34742.62 | D65: 5481.88 | E65: 441.62 | F65: 93.69 | G65: 1459.44 | H65: 39112.99 | I65: 219 | J65: =ROUND(IFERROR(C65,0)+IFERROR(D65,0)+IFERROR(E65,0)-IFERROR(F65,0)-IFERROR(G65,0)-IFERROR(H65,0),2)=0
A66: 45351 | B66: SMB | C66: 39112.99 | D66: 5634.48 | E66: 453.48 | F66: 168.59 | G66: 1152.42 | H66: 43879.94 | I66: 247 | J66: =ROUND(IFERROR(C66,0)+IFERROR(D66,0)+IFERROR(E66,0)-IFERROR(F66,0)-IFERROR(G66,0)-IFERROR(H66,0),2)=0
A67: 45382 | B67: SMB | C67: 43879.94 | D67: 5882.56 | E67: 390.39 | F67: 50.82 | G67: 1111.28 | H67: 48990.79 | I67: 275 | J67: =ROUND(IFERROR(C67,0)+IFERROR(D67,0)+IFERROR(E67,0)-IFERROR(F67,0)-IFERROR(G67,0)-IFERROR(H67,0),2)=0
A68: 45412 | B68: SMB | C68: 48990.79 | D68: 5487.24 | E68: 533.41 | F68: 112 | G68: 1030.07 | H68: 53869.37 | I68: 303 | J68: =ROUND(IFERROR(C68,0)+IFERROR(D68,0)+IFERROR(E68,0)-IFERROR(F68,0)-IFERROR(G68,0)-IFERROR(H68,0),2)=0
A69: 44957 | B69: Total | C69: 0 | D69: 7164.6 | H69: 7164.6 | I69: 101 | J69: =ROUND(IFERROR(C69,0)+IFERROR(D69,0)+IFERROR(E69,0)-IFERROR(F69,0)-IFERROR(G69,0)-IFERROR(H69,0),2)=0
A70: 44985 | B70: Total | C70: 7164.6 | D70: 7999.87 | E70: 54.51 | F70: 39.28 | G70: 392 | H70: 14787.7 | I70: 195 | J70: =ROUND(IFERROR(C70,0)+IFERROR(D70,0)+IFERROR(E70,0)-IFERROR(F70,0)-IFERROR(G70,0)-IFERROR(H70,0),2)=0
A71: 45016 | B71: Total | C71: 14787.7 | D71: 11718.94 | G71: 343 | H71: 26163.64 | I71: 311 | J71: =ROUND(IFERROR(C71,0)+IFERROR(D71,0)+IFERROR(E71,0)-IFERROR(F71,0)-IFERROR(G71,0)-IFERROR(H71,0),2)=0
A72: 45046 | B72: Total | C72: 26163.64 | D72: 10596.43 | E72: 66.39 | F72: 32.92 | G72: 2022 | H72: 34771.54 | I72: 417 | J72: =ROUND(IFERROR(C72,0)+IFERROR(D72,0)+IFERROR(E72,0)-IFERROR(F72,0)-IFERROR(G72,0)-IFERROR(H72,0),2)=0
A73: 45077 | B73: Total | C73: 34771.54 | D73: 13976.29 | E73: 158.72 | G73: 1407.72 | H73: 47498.83 | I73: 526 | J73: =ROUND(IFERROR(C73,0)+IFERROR(D73,0)+IFERROR(E73,0)-IFERROR(F73,0)-IFERROR(G73,0)-IFERROR(H73,0),2)=0
A74: 45107 | B74: Total | C74: 47498.83 | D74: 13105.28 | E74: 127.71 | F74: 47.5 | G74: 3995 | H74: 56689.32 | I74: 637 | J74: =ROUND(IFERROR(C74,0)+IFERROR(D74,0)+IFERROR(E74,0)-IFERROR(F74,0)-IFERROR(G74,0)-IFERROR(H74,0),2)=0
A75: 45138 | B75: Total | C75: 56689.32 | D75: 14933.86 | E75: 106.15 | F75: 220.44 | G75: 1474.93 | H75: 70033.96 | I75: 759 | J75: =ROUND(IFERROR(C75,0)+IFERROR(D75,0)+IFERROR(E75,0)-IFERROR(F75,0)-IFERROR(G75,0)-IFERROR(H75,0),2)=0
A76: 45169 | B76: Total | C76: 70033.96 | D76: 13814.45 | E76: 394.11 | F76: 83.58 | G76: 2906 | H76: 81252.94 | I76: 872 | J76: =ROUND(IFERROR(C76,0)+IFERROR(D76,0)+IFERROR(E76,0)-IFERROR(F76,0)-IFERROR(G76,0)-IFERROR(H76,0),2)=0
A77: 45199 | B77: Total | C77: 81252.94 | D77: 16224.3 | E77: 694.3 | F77: 64.87 | G77: 2775.85 | H77: 95330.82 | I77: 995 | J77: =ROUND(IFERROR(C77,0)+IFERROR(D77,0)+IFERROR(E77,0)-IFERROR(F77,0)-IFERROR(G77,0)-IFERROR(H77,0),2)=0
A78: 45230 | B78: Total | C78: 95330.82 | D78: 16751.71 | E78: 247.75 | F78: 75.2 | G78: 4041.78 | H78: 108213.3 | I78: 1124 | J78: =ROUND(IFERROR(C78,0)+IFERROR(D78,0)+IFERROR(E78,0)-IFERROR(F78,0)-IFERROR(G78,0)-IFERROR(H78,0),2)=0
A79: 45260 | B79: Total | C79: 108213.3 | D79: 18667.37 | E79: 323.42 | F79: 32.51 | G79: 3461.75 | H79: 123709.83 | I79: 1248 | J79: =ROUND(IFERROR(C79,0)+IFERROR(D79,0)+IFERROR(E79,0)-IFERROR(F79,0)-IFERROR(G79,0)-IFERROR(H79,0),2)=0
A80: 45291 | B80: Total | C80: 123709.83 | D80: 20088.21 | E80: 490.81 | F80: 39.06 | G80: 6803.57 | H80: 137446.22 | I80: 1365 | J80: =ROUND(IFERROR(C80,0)+IFERROR(D80,0)+IFERROR(E80,0)-IFERROR(F80,0)-IFERROR(G80,0)-IFERROR(H80,0),2)=0
A81: 45322 | B81: Total | C81: 137446.22 | D81: 20506.38 | E81: 562.92 | F81: 241.39 | G81: 5183.44 | H81: 153090.69 | I81: 1489 | J81: =ROUND(IFERROR(C81,0)+IFERROR(D81,0)+IFERROR(E81,0)-IFERROR(F81,0)-IFERROR(G81,0)-IFERROR(H81,0),2)=0
A82: 45351 | B82: Total | C82: 153090.69 | D82: 22176.48 | E82: 678.69 | F82: 296.23 | G82: 5556.67 | H82: 170092.96 | I82: 1645 | J82: =ROUND(IFERROR(C82,0)+IFERROR(D82,0)+IFERROR(E82,0)-IFERROR(F82,0)-IFERROR(G82,0)-IFERROR(H82,0),2)=0
A83: 45382 | B83: Total | C83: 170092.96 | D83: 22649.56 | E83: 390.39 | F83: 50.82 | G83: 5677.78 | H83: 187404.31 | I83: 1788 | J83: =ROUND(IFERROR(C83,0)+IFERROR(D83,0)+IFERROR(E83,0)-IFERROR(F83,0)-IFERROR(G83,0)-IFERROR(H83,0),2)=0
A84: 45412 | B84: Total | C84: 187404.31 | D84: 22702.99 | E84: 697.93 | F84: 112 | G84: 5984.14 | H84: 204709.09 | I84: 1941 | J84: =ROUND(IFERROR(C84,0)+IFERROR(D84,0)+IFERROR(E84,0)-IFERROR(F84,0)-IFERROR(G84,0)-IFERROR(H84,0),2)=0

Sheet Data_Costs
A1: Data_Costs
A2: Source: stg_marketing_spend, stg_support_costs, mart_a2_01_new_paying_customers (verbatim exports). Three blocks: marketing spend by segment x channel, support costs by category (incl. G&A), and new paying customers by month x segment.
A4: Block A -- Marketing spend by segment x channel (stg_marketing_spend)
A5: month | B5: segment | C5: channel | D5: spend | E5: new_users_acquired
A6: 44927 | B6: B2C | C6: Content | D6: 4804.82 | E6: 150
A7: 44927 | B7: B2C | C7: Organic | D7: 3100.99 | E7: 210
A8: 44927 | B8: B2C | C8: Paid Search | D8: 15854.35 | E8: 290
A9: 44927 | B9: B2C | C9: Paid Social | D9: 11150.23 | E9: 233
A10: 44927 | B10: Enterprise | C10: Content | D10: 3268.88 | E10: 0
A11: 44927 | B11: Enterprise | C11: Sales Team | D11: 17514.6 | E11: 3
A12: 44927 | B12: SMB | C12: Content | D12: 2220.16 | E12: 8
A13: 44927 | B13: SMB | C13: Paid Search | D13: 4325.02 | E13: 15
A14: 44927 | B14: SMB | C14: Paid Social | D14: 3437.9 | E14: 9
A15: 44958 | B15: B2C | C15: Content | D15: 5557.39 | E15: 189
A16: 44958 | B16: B2C | C16: Organic | D16: 3258.38 | E16: 249
A17: 44958 | B17: B2C | C17: Paid Search | D17: 14003.44 | E17: 295
... A149: 45383 | B149: SMB | C149: Paid Social | D149: 7055.92 | E149: 14
A151: Block B -- Support costs by category, incl. G&A (stg_support_costs)
A152: month | B152: category | C152: amount
A153: 44927 | B153: CS Salaries | C153: 30417.51
A154: 44927 | B154: Content Production | C154: 23288.62
A155: 44927 | B155: G&A | C155: 22014.85
A156: 44927 | B156: Infrastructure | C156: 19317.85
A157: 44958 | B157: CS Salaries | C157: 33890.33
A158: 44958 | B158: Content Production | C158: 26492.33
A159: 44958 | B159: G&A | C159: 21940.26
A160: 44958 | B160: Infrastructure | C160: 17941.03
A161: 44986 | B161: CS Salaries | C161: 34952.8
A162: 44986 | B162: Content Production | C162: 28516.62
A163: 44986 | B163: G&A | C163: 24450.65
A164: 44986 | B164: Infrastructure | C164: 20105.1
... A216: 45383 | B216: Infrastructure | C216: 30597.71
A218: Block C -- New paying customers by month x segment (mart_a2_01_new_paying_customers)
A219: month | B219: segment | C219: new_paying_customers
A220: 44927 | B220: B2B | C220: 11
A221: 44927 | B221: B2C | C221: 90
A222: 44927 | B222: Enterprise | C222: 2
A223: 44927 | B223: SMB | C223: 9
A224: 44927 | B224: Total | C224: 101
A225: 44958 | B225: B2B | C225: 17
A226: 44958 | B226: B2C | C226: 85
A227: 44958 | B227: Enterprise | C227: 2
A228: 44958 | B228: SMB | C228: 15
A229: 44958 | B229: Total | C229: 102
A230: 44986 | B230: B2B | C230: 21
A231: 44986 | B231: B2C | C231: 102
... A299: 45383 | B299: Total | C299: 239

Sheet Data_Survival
A1: Data_Survival
A2: Source: mart_a2_10_survival_curve.sql (verbatim export). Logo and dollar survival curves by segment, k=0..15 months since signup. Used by UnitEconomics to build the 60-month lifetime curve (observed k=0..k_rel, then an extrapolated tail).
A4: segment | B4: k | C4: exposed_n | D4: active_n | E4: logo_survival | F4: mrr_at_k_sum | G4: mrr_at_0_sum | H4: dollar_retention | I4: arpa_at_signup
A5: B2B | B5: 0 | C5: 470 | D5: 469 | E5: 0.9979 | F5: 155160.72 | G5: 155160.72 | H5: 1 | I5: 330.13
A6: B2B | B6: 1 | C6: 427 | D6: 416 | E6: 0.9742 | F6: 139866.53 | G6: 141258.48 | H6: 0.9901 | I6: 330.82
A7: B2B | B7: 2 | C7: 383 | D7: 359 | E7: 0.9373 | F7: 121567.6 | G7: 126630.92 | H7: 0.96 | I7: 330.63
A8: B2B | B8: 3 | C8: 340 | D8: 305 | E8: 0.8971 | F8: 104251.39 | G8: 112581.44 | H8: 0.926 | I8: 331.12
A9: B2B | B9: 4 | C9: 300 | D9: 259 | E9: 0.8633 | F9: 90044.1 | G9: 99344.56 | H9: 0.9064 | I9: 331.15
A10: B2B | B10: 5 | C10: 262 | D10: 220 | E10: 0.8397 | F10: 76410.02 | G10: 86359.6 | H10: 0.8848 | I10: 329.62
A11: B2B | B11: 6 | C11: 229 | D11: 189 | E11: 0.8253 | F11: 64619.21 | G11: 74368.48 | H11: 0.8689 | I11: 324.75
A12: B2B | B12: 7 | C12: 200 | D12: 166 | E12: 0.83 | F12: 56628.31 | G12: 64688.52 | H12: 0.8754 | I12: 323.44
A13: B2B | B13: 8 | C13: 170 | D13: 137 | E13: 0.8059 | F13: 46918.15 | G13: 54907.72 | H13: 0.8545 | I13: 322.99
A14: B2B | B14: 9 | C14: 144 | D14: 118 | E14: 0.8194 | F14: 40099.7 | G14: 46929.52 | H14: 0.8545 | I14: 325.9
A15: B2B | B15: 10 | C15: 116 | D15: 95 | E15: 0.819 | F15: 30395.19 | G15: 37368.16 | H15: 0.8134 | I15: 322.14
A16: B2B | B16: 11 | C16: 94 | D16: 77 | E16: 0.8191 | F16: 25161.4 | G16: 29806.88 | H16: 0.8441 | I16: 317.09
... A84: Total | B84: 15 | C84: 101 | D84: 47 | E84: 0.4653 | F84: 4452.65 | G84: 7164.6 | H84: 0.6215 | I84: 70.94

Sheet Answers_Q1_Q4
A1: Answers_Q1_Q4
A2: The four ad-hoc questions. Q1 (MRR by segment) and Q3 (active subs by segment x plan) are rebuilt with formulas from Data_MRR / the Assumptions starting-stock block. Q2 (Q1-24 retention) and Q4 (NDR T12M) link to small data blocks exported from mart_q2_retention_q1_24 / mart_q4_ndr_t12m: their definitions (M-06 renewal-event retention; M-08/M-09/M-10 NDR/GRR/expansion-contraction) require row-level subscription-period data and a customer-level cohort join that are impractical to rebuild as spreadsheet formulas -- that computation lives in SQL (sql/marts/mart_q2_retention_q1_24.sql, mart_q4_ndr_t12m.sql); this tab links the finished mart output instead of re-deriving it.
A4: Q1 -- MRR by segment, Apr-24 (M-01..M-04; formula from Data_MRR)
A5: Segment | B5: MRR Apr-24 | C5: % of total
A6: B2C | B6: =SUMIFS(Data_MRR!$H:$H,Data_MRR!$B:$B,"B2C",Data_MRR!$A:$A,Assumptions!$B$10) | C6: =B6/$B$9
A7: SMB | B7: =SUMIFS(Data_MRR!$H:$H,Data_MRR!$B:$B,"SMB",Data_MRR!$A:$A,Assumptions!$B$10) | C7: =B7/$B$9
A8: Enterprise | B8: =SUMIFS(Data_MRR!$H:$H,Data_MRR!$B:$B,"Enterprise",Data_MRR!$A:$A,Assumptions!$B$10) | C8: =B8/$B$9
A9: Total (= sum of segments) | B9: =SUM(B6:B8) | C9: =B9/$B$9
A11: Q2 -- Q1-2024 retention, B2C vs B2B (M-06 primary; linked from mart_q2_retention_q1_24)
A12: Segment | B12: Logo retention (all plans) | C12: $ retention (all plans)
A13: B2C | B13: =SUMPRODUCT(($A$21:$A$40="B2C")*($B$21:$B$40="all")*($C$21:$C$40="M06_primary")*$G$21:$G$40) | C13: =SUMPRODUCT(($A$21:$A$40="B2C")*($B$21:$B$40="all")*($C$21:$C$40="M06_primary")*$J$21:$J$40)
A14: SMB | B14: =SUMPRODUCT(($A$21:$A$40="SMB")*($B$21:$B$40="all")*($C$21:$C$40="M06_primary")*$G$21:$G$40) | C14: =SUMPRODUCT(($A$21:$A$40="SMB")*($B$21:$B$40="all")*($C$21:$C$40="M06_primary")*$J$21:$J$40)
A15: Enterprise | B15: =SUMPRODUCT(($A$21:$A$40="Enterprise")*($B$21:$B$40="all")*($C$21:$C$40="M06_primary")*$G$21:$G$40) | C15: =SUMPRODUCT(($A$21:$A$40="Enterprise")*($B$21:$B$40="all")*($C$21:$C$40="M06_primary")*$J$21:$J$40)
A16: B2B | B16: =SUMPRODUCT(($A$21:$A$40="B2B")*($B$21:$B$40="all")*($C$21:$C$40="M06_primary")*$G$21:$G$40) | C16: =SUMPRODUCT(($A$21:$A$40="B2B")*($B$21:$B$40="all")*($C$21:$C$40="M06_primary")*$J$21:$J$40)
A17: Total | B17: =SUMPRODUCT(($A$21:$A$40="Total")*($B$21:$B$40="all")*($C$21:$C$40="M06_primary")*$G$21:$G$40) | C17: =SUMPRODUCT(($A$21:$A$40="Total")*($B$21:$B$40="all")*($C$21:$C$40="M06_primary")*$J$21:$J$40)
A19: Data block below: mart_q2_retention_q1_24 (M-06 renewal-event basis: renewed / (renewed + churned), over subscriptions with end_date in 2024-01-01..2024-03-31).
A20: segment | B20: split | C20: method | D20: n_renewed | E20: n_churned | F20: n_ended | G20: logo_rate | H20: dollar_numerator | I20: dollar_denominator | J20: dollar_rate
A21: B2B | B21: all | C21: M06_primary | D21: 301 | E21: 20 | F21: 321 | G21: 0.9377 | H21: 89702.34 | I21: 94196.92 | J21: 0.9523
A22: B2B | B22: all | C22: M07_crosscheck | F22: 261 | G22: 0.9349
A23: B2B | B23: annual | C23: M06_primary | D23: 28 | E23: 2 | F23: 30 | G23: 0.9333 | H23: 8256.49 | I23: 9223.16 | J23: 0.8952
A24: B2B | B24: monthly | C24: M06_primary | D24: 273 | E24: 18 | F24: 291 | G24: 0.9381 | H24: 81445.85 | I24: 84973.76 | J24: 0.9585
A25: B2C | B25: all | C25: M06_primary | D25: 1936 | E25: 226 | F25: 2162 | G25: 0.8955 | H25: 93635.5 | I25: 104662.25 | J25: 0.8946
A26: B2C | B26: all | C26: M07_crosscheck | F26: 1104 | G26: 0.8261
A27: B2C | B27: annual | C27: M06_primary | D27: 78 | E27: 3 | F27: 81 | G27: 0.963 | H27: 2593.5 | I27: 2693.25 | J27: 0.963
A28: B2C | B28: monthly | C28: M06_primary | D28: 1858 | E28: 223 | F28: 2081 | G28: 0.8928 | H28: 91042 | I28: 101969 | J28: 0.8928
A29: Enterprise | B29: all | C29: M06_primary | D29: 31 | E29: 2 | F29: 33 | G29: 0.9394 | H29: 30443.54 | I29: 32187.37 | J29: 0.9458
A30: Enterprise | B30: all | C30: M07_crosscheck | F30: 66 | G30: 0.9697
A31: Enterprise | B31: annual | C31: M06_primary | D31: 6 | E31: 1 | F31: 7 | G31: 0.8571 | H31: 4864.99 | I31: 5775 | J31: 0.8424
A32: Enterprise | B32: monthly | C32: M06_primary | D32: 25 | E32: 1 | F32: 26 | G32: 0.9615 | H32: 25578.55 | I32: 26412.37 | J32: 0.9684
A33: SMB | B33: all | C33: M06_primary | D33: 270 | E33: 18 | F33: 288 | G33: 0.9375 | H33: 59258.8 | I33: 62009.55 | J33: 0.9556
A34: SMB | B34: all | C34: M07_crosscheck | F34: 195 | G34: 0.9231
A35: SMB | B35: annual | C35: M06_primary | D35: 22 | E35: 1 | F35: 23 | G35: 0.9565 | H35: 3391.5 | I35: 3448.16 | J35: 0.9836
A36: SMB | B36: monthly | C36: M06_primary | D36: 248 | E36: 17 | F36: 265 | G36: 0.9358 | H36: 55867.3 | I36: 58561.39 | J36: 0.954
A37: Total | B37: all | C37: M06_primary | D37: 2237 | E37: 246 | F37: 2483 | G37: 0.9009 | H37: 183337.84 | I37: 198859.17 | J37: 0.9219
A38: Total | B38: all | C38: M07_crosscheck | F38: 1365 | G38: 0.8469
A39: Total | B39: annual | C39: M06_primary | D39: 106 | E39: 5 | F39: 111 | G39: 0.955 | H39: 10849.99 | I39: 11916.41 | J39: 0.9105
A40: Total | B40: monthly | C40: M06_primary | D40: 2131 | E40: 241 | F40: 2372 | G40: 0.8984 | H40: 172487.85 | I40: 186942.76 | J40: 0.9227
A42: Q3 -- Active subscriptions, Apr-24, by segment x plan (M-02; formula from Assumptions starting stock)
A43: Segment | B43: Monthly | C43: Annual | D43: Total
A44: B2C | B44: =SUMIFS(Assumptions!$C$29:$C$34,Assumptions!$A$29:$A$34,"B2C",Assumptions!$B$29:$B$34,"monthly") | C44: =SUMIFS(Assumptions!$C$29:$C$34,Assumptions!$A$29:$A$34,"B2C",Assumptions!$B$29:$B$34,"annual") | D44: =B44+C44
A45: SMB | B45: =SUMIFS(Assumptions!$C$29:$C$34,Assumptions!$A$29:$A$34,"SMB",Assumptions!$B$29:$B$34,"monthly") | C45: =SUMIFS(Assumptions!$C$29:$C$34,Assumptions!$A$29:$A$34,"SMB",Assumptions!$B$29:$B$34,"annual") | D45: =B45+C45
A46: Enterprise | B46: =SUMIFS(Assumptions!$C$29:$C$34,Assumptions!$A$29:$A$34,"Enterprise",Assumptions!$B$29:$B$34,"monthly") | C46: =SUMIFS(Assumptions!$C$29:$C$34,Assumptions!$A$29:$A$34,"Enterprise",Assumptions!$B$29:$B$34,"annual") | D46: =B46+C46
A47: Total | B47: =SUM(B44:B46) | C47: =SUM(C44:C46) | D47: =SUM(D44:D46)
A49: Q4 -- NDR T12M, company & segment (M-08/M-09; linked from mart_q4_ndr_t12m)
A50: Segment | B50: NDR (T12M) | C50: GRR (T12M)
A51: B2C | B51: =SUMPRODUCT(($B$59:$B$68="B2C")*($A$59:$A$68="M08_M09_M10")*$I$59:$I$68) | C51: =SUMPRODUCT(($B$59:$B$68="B2C")*($A$59:$A$68="M08_M09_M10")*$J$59:$J$68)
A52: SMB | B52: =SUMPRODUCT(($B$59:$B$68="SMB")*($A$59:$A$68="M08_M09_M10")*$I$59:$I$68) | C52: =SUMPRODUCT(($B$59:$B$68="SMB")*($A$59:$A$68="M08_M09_M10")*$J$59:$J$68)
A53: Enterprise | B53: =SUMPRODUCT(($B$59:$B$68="Enterprise")*($A$59:$A$68="M08_M09_M10")*$I$59:$I$68) | C53: =SUMPRODUCT(($B$59:$B$68="Enterprise")*($A$59:$A$68="M08_M09_M10")*$J$59:$J$68)
A54: B2B | B54: =SUMPRODUCT(($B$59:$B$68="B2B")*($A$59:$A$68="M08_M09_M10")*$I$59:$I$68) | C54: =SUMPRODUCT(($B$59:$B$68="B2B")*($A$59:$A$68="M08_M09_M10")*$J$59:$J$68)
A55: Total | B55: =SUMPRODUCT(($B$59:$B$68="Total")*($A$59:$A$68="M08_M09_M10")*$I$59:$I$68) | C55: =SUMPRODUCT(($B$59:$B$68="Total")*($A$59:$A$68="M08_M09_M10")*$J$59:$J$68)
A57: Data block below: mart_q4_ndr_t12m (M-08 snapshot method: customers active on 2023-04-30; NDR = their Apr-24 MRR / their Apr-23 MRR; GRR caps expansion at 100%).
A58: method | B58: segment | C58: base_customers | D58: start_mrr | E58: expansion_mrr | F58: contraction_mrr | G58: churn_mrr | H58: end_mrr | I58: ndr | J58: grr
A59: M08_M09_M10 | B59: B2B | C59: 64 | D59: 19301.54 | E59: 1329.43 | F59: 168.42 | G59: 4976.57 | H59: 15485.98 | I59: 0.8023 | J59: 0.7334
A60: renewal_crosscheck | B60: B2B | C60: 832 | E60: 4872.9 | F60: 1263.6
A61: M08_M09_M10 | B61: B2C | C61: 353 | D61: 15470 | E61: 0 | F61: 0 | G61: 8806 | H61: 6664 | I61: 0.4308 | J61: 0.4308
A62: renewal_crosscheck | B62: B2C | C62: 5803 | E62: 0 | F62: 0
A63: M08_M09_M10 | B63: Enterprise | C63: 12 | D63: 10230 | E63: 42.63 | F63: 127.64 | G63: 2805 | H63: 7339.99 | I63: 0.7175 | J63: 0.7133
A64: renewal_crosscheck | B64: Enterprise | C64: 75 | E64: 956.19 | F64: 470.08
A65: M08_M09_M10 | B65: SMB | C65: 52 | D65: 9071.54 | E65: 1286.8 | F65: 40.78 | G65: 2171.57 | H65: 8145.99 | I65: 0.898 | J65: 0.7561
A66: renewal_crosscheck | B66: SMB | C66: 757 | E66: 3916.71 | F66: 793.52
A67: M08_M09_M10 | B67: Total | C67: 417 | D67: 34771.54 | E67: 1329.43 | F67: 168.42 | G67: 13782.57 | H67: 22149.98 | I67: 0.637 | J67: 0.5988
A68: renewal_crosscheck | B68: Total | C68: 6635 | E68: 4872.9 | F68: 1263.6

Sheet UnitEconomics
A1: UnitEconomics
A2: Source: Data_Costs, Data_MRR, Data_Survival + Assumptions (D-05/D-06/D-07, M-12..M-15, A-15..A-18, A-23). Fully loaded CAC, gross margin, ARPA, the 60-month survival-based lifetime curve, LTV, LTV:CAC, CAC payback and the retention-adjusted payback, by segment -- all computed with formulas from the Data_* tabs, cross-checked on the Checks tab against mart_a2_12_unit_economics_summary within 1%.
A4: G&A allocation build (D-05): company-level marketing, COGS (non-G&A support costs) and G&A pool, T6M and T16M
A5: Metric | B5: T6M (Nov-23..Apr-24) | C5: T16M (Jan-23..Apr-24)
A6: Total marketing spend (all segments) | B6: =SUMIFS(Data_Costs!$D$6:$D$149,Data_Costs!$A$6:$A$149,">="&Assumptions!$B$12,Data_Costs!$A$6:$A$149,"<="&Assumptions!$B$13) | C6: =SUMIFS(Data_Costs!$D$6:$D$149,Data_Costs!$A$6:$A$149,">="&Assumptions!$B$15,Data_Costs!$A$6:$A$149,"<="&Assumptions!$B$13)
A7: Total support costs, non-G&A (= company COGS) | B7: =SUMIFS(Data_Costs!$C$153:$C$216,Data_Costs!$B$153:$B$216,"CS Salaries",Data_Costs!$A$153:$A$216,">="&Assumptions!$B$12,Data_Costs!$A$153:$A$216,"<="&Assumptions!$B$13)+SUMIFS(Data_Costs!$C$153:$C$216,Data_Costs!$B$153:$B$216,"Infrastructure",Data_Costs!$A$153:$A$216,">="&Assumptions!$B$12,Data_Costs!$A$153:$A$216,"<="&Assumptions!$B$13)+SUMIFS(Data_Costs!$C$153:$C$216,Data_Costs!$B$153:$B$216,"Content Production",Data_Costs!$A$153:$A$216,">="&Assumptions!$B$12,Data_Costs!$A$153:$A$216,"<="&Assumptions!$B$13) | C7: =SUMIFS(Data_Costs!$C$153:$C$216,Data_Costs!$B$153:$B$216,"CS Salaries",Data_Costs!$A$153:$A$216,">="&Assumptions!$B$15,Data_Costs!$A$153:$A$216,"<="&Assumptions!$B$13)+SUMIFS(Data_Costs!$C$153:$C$216,Data_Costs!$B$153:$B$216,"Infrastructure",Data_Costs!$A$153:$A$216,">="&Assumptions!$B$15,Data_Costs!$A$153:$A$216,"<="&Assumptions!$B$13)+SUMIFS(Data_Costs!$C$153:$C$216,Data_Costs!$B$153:$B$216,"Content Production",Data_Costs!$A$153:$A$216,">="&Assumptions!$B$15,Data_Costs!$A$153:$A$216,"<="&Assumptions!$B$13)
A8: Total G&A | B8: =SUMIFS(Data_Costs!$C$153:$C$216,Data_Costs!$B$153:$B$216,"G&A",Data_Costs!$A$153:$A$216,">="&Assumptions!$B$12,Data_Costs!$A$153:$A$216,"<="&Assumptions!$B$13) | C8: =SUMIFS(Data_Costs!$C$153:$C$216,Data_Costs!$B$153:$B$216,"G&A",Data_Costs!$A$153:$A$216,">="&Assumptions!$B$15,Data_Costs!$A$153:$A$216,"<="&Assumptions!$B$13)
A9: Acquisition share of G&A = marketing / (marketing + COGS) | B9: =B6/(B6+B7) | C9: =C6/(C6+C7)
A10: Allocated G&A pool = acquisition share x total G&A | B10: =B9*B8 | C10: =C9*C8
A12: Monthly ARPA (by segment) & company GM% helper (T6M window, Nov-23..Apr-24). M-12: revenue=MRR, COGS=CS Salaries+Infrastructure+Content, all allocated by MRR share -> GM% is uniform across segments by construction (test_a2_gm_base_uniform)
A13: Month-end | B13: Revenue (Total MRR) | C13: COGS (non-G&A) | D13: GM% (month) | E13: B2C ARPA | F13: SMB ARPA | G13: Enterprise ARPA | I13: Month-start (helper, for Data_Costs lookups)
A14: 45260 | B14: =SUMIFS(Data_MRR!$H$5:$H$84,Data_MRR!$B$5:$B$84,"Total",Data_MRR!$A$5:$A$84,$A14) | C14: =SUMIFS(Data_Costs!$C$153:$C$216,Data_Costs!$B$153:$B$216,"CS Salaries",Data_Costs!$A$153:$A$216,$I14)+SUMIFS(Data_Costs!$C$153:$C$216,Data_Costs!$B$153:$B$216,"Infrastructure",Data_Costs!$A$153:$A$216,$I14)+SUMIFS(Data_Costs!$C$153:$C$216,Data_Costs!$B$153:$B$216,"Content Production",Data_Costs!$A$153:$A$216,$I14) | D14: =1-C14/B14 | E14: =SUMIFS(Data_MRR!$H$5:$H$84,Data_MRR!$B$5:$B$84,"B2C",Data_MRR!$A$5:$A$84,$A14)/SUMIFS(Data_MRR!$I$5:$I$84,Data_MRR!$B$5:$B$84,"B2C",Data_MRR!$A$5:$A$84,$A14) | F14: =SUMIFS(Data_MRR!$H$5:$H$84,Data_MRR!$B$5:$B$84,"SMB",Data_MRR!$A$5:$A$84,$A14)/SUMIFS(Data_MRR!$I$5:$I$84,Data_MRR!$B$5:$B$84,"SMB",Data_MRR!$A$5:$A$84,$A14) | G14: =SUMIFS(Data_MRR!$H$5:$H$84,Data_MRR!$B$5:$B$84,"Enterprise",Data_MRR!$A$5:$A$84,$A14)/SUMIFS(Data_MRR!$I$5:$I$84,Data_MRR!$B$5:$B$84,"Enterprise",Data_MRR!$A$5:$A$84,$A14) | I14: 45231
A15: 45291 | B15: =SUMIFS(Data_MRR!$H$5:$H$84,Data_MRR!$B$5:$B$84,"Total",Data_MRR!$A$5:$A$84,$A15) | C15: =SUMIFS(Data_Costs!$C$153:$C$216,Data_Costs!$B$153:$B$216,"CS Salaries",Data_Costs!$A$153:$A$216,$I15)+SUMIFS(Data_Costs!$C$153:$C$216,Data_Costs!$B$153:$B$216,"Infrastructure",Data_Costs!$A$153:$A$216,$I15)+SUMIFS(Data_Costs!$C$153:$C$216,Data_Costs!$B$153:$B$216,"Content Production",Data_Costs!$A$153:$A$216,$I15) | D15: =1-C15/B15 | E15: =SUMIFS(Data_MRR!$H$5:$H$84,Data_MRR!$B$5:$B$84,"B2C",Data_MRR!$A$5:$A$84,$A15)/SUMIFS(Data_MRR!$I$5:$I$84,Data_MRR!$B$5:$B$84,"B2C",Data_MRR!$A$5:$A$84,$A15) | F15: =SUMIFS(Data_MRR!$H$5:$H$84,Data_MRR!$B$5:$B$84,"SMB",Data_MRR!$A$5:$A$84,$A15)/SUMIFS(Data_MRR!$I$5:$I$84,Data_MRR!$B$5:$B$84,"SMB",Data_MRR!$A$5:$A$84,$A15) | G15: =SUMIFS(Data_MRR!$H$5:$H$84,Data_MRR!$B$5:$B$84,"Enterprise",Data_MRR!$A$5:$A$84,$A15)/SUMIFS(Data_MRR!$I$5:$I$84,Data_MRR!$B$5:$B$84,"Enterprise",Data_MRR!$A$5:$A$84,$A15) | I15: 45261
A16: 45322 | B16: =SUMIFS(Data_MRR!$H$5:$H$84,Data_MRR!$B$5:$B$84,"Total",Data_MRR!$A$5:$A$84,$A16) | C16: =SUMIFS(Data_Costs!$C$153:$C$216,Data_Costs!$B$153:$B$216,"CS Salaries",Data_Costs!$A$153:$A$216,$I16)+SUMIFS(Data_Costs!$C$153:$C$216,Data_Costs!$B$153:$B$216,"Infrastructure",Data_Costs!$A$153:$A$216,$I16)+SUMIFS(Data_Costs!$C$153:$C$216,Data_Costs!$B$153:$B$216,"Content Production",Data_Costs!$A$153:$A$216,$I16) | D16: =1-C16/B16 | E16: =SUMIFS(Data_MRR!$H$5:$H$84,Data_MRR!$B$5:$B$84,"B2C",Data_MRR!$A$5:$A$84,$A16)/SUMIFS(Data_MRR!$I$5:$I$84,Data_MRR!$B$5:$B$84,"B2C",Data_MRR!$A$5:$A$84,$A16) | F16: =SUMIFS(Data_MRR!$H$5:$H$84,Data_MRR!$B$5:$B$84,"SMB",Data_MRR!$A$5:$A$84,$A16)/SUMIFS(Data_MRR!$I$5:$I$84,Data_MRR!$B$5:$B$84,"SMB",Data_MRR!$A$5:$A$84,$A16) | G16: =SUMIFS(Data_MRR!$H$5:$H$84,Data_MRR!$B$5:$B$84,"Enterprise",Data_MRR!$A$5:$A$84,$A16)/SUMIFS(Data_MRR!$I$5:$I$84,Data_MRR!$B$5:$B$84,"Enterprise",Data_MRR!$A$5:$A$84,$A16) | I16: 45292
A17: 45351 | B17: =SUMIFS(Data_MRR!$H$5:$H$84,Data_MRR!$B$5:$B$84,"Total",Data_MRR!$A$5:$A$84,$A17) | C17: =SUMIFS(Data_Costs!$C$153:$C$216,Data_Costs!$B$153:$B$216,"CS Salaries",Data_Costs!$A$153:$A$216,$I17)+SUMIFS(Data_Costs!$C$153:$C$216,Data_Costs!$B$153:$B$216,"Infrastructure",Data_Costs!$A$153:$A$216,$I17)+SUMIFS(Data_Costs!$C$153:$C$216,Data_Costs!$B$153:$B$216,"Content Production",Data_Costs!$A$153:$A$216,$I17) | D17: =1-C17/B17 | E17: =SUMIFS(Data_MRR!$H$5:$H$84,Data_MRR!$B$5:$B$84,"B2C",Data_MRR!$A$5:$A$84,$A17)/SUMIFS(Data_MRR!$I$5:$I$84,Data_MRR!$B$5:$B$84,"B2C",Data_MRR!$A$5:$A$84,$A17) | F17: =SUMIFS(Data_MRR!$H$5:$H$84,Data_MRR!$B$5:$B$84,"SMB",Data_MRR!$A$5:$A$84,$A17)/SUMIFS(Data_MRR!$I$5:$I$84,Data_MRR!$B$5:$B$84,"SMB",Data_MRR!$A$5:$A$84,$A17) | G17: =SUMIFS(Data_MRR!$H$5:$H$84,Data_MRR!$B$5:$B$84,"Enterprise",Data_MRR!$A$5:$A$84,$A17)/SUMIFS(Data_MRR!$I$5:$I$84,Data_MRR!$B$5:$B$84,"Enterprise",Data_MRR!$A$5:$A$84,$A17) | I17: 45323
A18: 45382 | B18: =SUMIFS(Data_MRR!$H$5:$H$84,Data_MRR!$B$5:$B$84,"Total",Data_MRR!$A$5:$A$84,$A18) | C18: =SUMIFS(Data_Costs!$C$153:$C$216,Data_Costs!$B$153:$B$216,"CS Salaries",Data_Costs!$A$153:$A$216,$I18)+SUMIFS(Data_Costs!$C$153:$C$216,Data_Costs!$B$153:$B$216,"Infrastructure",Data_Costs!$A$153:$A$216,$I18)+SUMIFS(Data_Costs!$C$153:$C$216,Data_Costs!$B$153:$B$216,"Content Production",Data_Costs!$A$153:$A$216,$I18) | D18: =1-C18/B18 | E18: =SUMIFS(Data_MRR!$H$5:$H$84,Data_MRR!$B$5:$B$84,"B2C",Data_MRR!$A$5:$A$84,$A18)/SUMIFS(Data_MRR!$I$5:$I$84,Data_MRR!$B$5:$B$84,"B2C",Data_MRR!$A$5:$A$84,$A18) | F18: =SUMIFS(Data_MRR!$H$5:$H$84,Data_MRR!$B$5:$B$84,"SMB",Data_MRR!$A$5:$A$84,$A18)/SUMIFS(Data_MRR!$I$5:$I$84,Data_MRR!$B$5:$B$84,"SMB",Data_MRR!$A$5:$A$84,$A18) | G18: =SUMIFS(Data_MRR!$H$5:$H$84,Data_MRR!$B$5:$B$84,"Enterprise",Data_MRR!$A$5:$A$84,$A18)/SUMIFS(Data_MRR!$I$5:$I$84,Data_MRR!$B$5:$B$84,"Enterprise",Data_MRR!$A$5:$A$84,$A18) | I18: 45352
A19: 45412 | B19: =SUMIFS(Data_MRR!$H$5:$H$84,Data_MRR!$B$5:$B$84,"Total",Data_MRR!$A$5:$A$84,$A19) | C19: =SUMIFS(Data_Costs!$C$153:$C$216,Data_Costs!$B$153:$B$216,"CS Salaries",Data_Costs!$A$153:$A$216,$I19)+SUMIFS(Data_Costs!$C$153:$C$216,Data_Costs!$B$153:$B$216,"Infrastructure",Data_Costs!$A$153:$A$216,$I19)+SUMIFS(Data_Costs!$C$153:$C$216,Data_Costs!$B$153:$B$216,"Content Production",Data_Costs!$A$153:$A$216,$I19) | D19: =1-C19/B19 | E19: =SUMIFS(Data_MRR!$H$5:$H$84,Data_MRR!$B$5:$B$84,"B2C",Data_MRR!$A$5:$A$84,$A19)/SUMIFS(Data_MRR!$I$5:$I$84,Data_MRR!$B$5:$B$84,"B2C",Data_MRR!$A$5:$A$84,$A19) | F19: =SUMIFS(Data_MRR!$H$5:$H$84,Data_MRR!$B$5:$B$84,"SMB",Data_MRR!$A$5:$A$84,$A19)/SUMIFS(Data_MRR!$I$5:$I$84,Data_MRR!$B$5:$B$84,"SMB",Data_MRR!$A$5:$A$84,$A19) | G19: =SUMIFS(Data_MRR!$H$5:$H$84,Data_MRR!$B$5:$B$84,"Enterprise",Data_MRR!$A$5:$A$84,$A19)/SUMIFS(Data_MRR!$I$5:$I$84,Data_MRR!$B$5:$B$84,"Enterprise",Data_MRR!$A$5:$A$84,$A19) | I19: 45383
A20: T6M average GM% (base, D-17) | D20: =AVERAGE(D14:D19)
A21: Apr-24 run-rate GM% (single month, D-17 sensitivity) | D21: =D19
A22: ARPA T6M avg by segment -> | E22: =AVERAGE(E14:E19) | F22: =AVERAGE(F14:F19) | G22: =AVERAGE(G14:G19)
A24: GM% selected (per Assumptions GM-basis selector) | B24: =IF(Assumptions!$B$7="T6M avg",D20,D21)
A26: Headline unit economics by segment (D-05/D-06/M-12..M-15; GM% uniform by construction -- see note above)
A27: Segment | B27: Marketing spend T6M | C27: Marketing spend T16M | D27: New paying customers T6M | E27: New paying customers T16M | F27: Allocated G&A T6M | G27: Allocated G&A T16M | H27: CAC fully loaded T6M | I27: CAC fully loaded T16M | J27: ARPA (T6M avg) | K27: GM% (selected) | L27: Revenue Apr-24 | M27: Lifetime, $ curve (60mo cap) | N27: LTV (60mo cap) | O27: LTV:CAC (T6M)
A28: B2C | B28: =SUMIFS(Data_Costs!$D$6:$D$149,Data_Costs!$B$6:$B$149,"B2C",Data_Costs!$A$6:$A$149,">="&Assumptions!$B$12,Data_Costs!$A$6:$A$149,"<="&Assumptions!$B$13) | C28: =SUMIFS(Data_Costs!$D$6:$D$149,Data_Costs!$B$6:$B$149,"B2C",Data_Costs!$A$6:$A$149,">="&Assumptions!$B$15,Data_Costs!$A$6:$A$149,"<="&Assumptions!$B$13) | D28: =SUMIFS(Data_Costs!$C$220:$C$299,Data_Costs!$B$220:$B$299,"B2C",Data_Costs!$A$220:$A$299,">="&Assumptions!$B$12,Data_Costs!$A$220:$A$299,"<="&Assumptions!$B$13) | E28: =SUMIFS(Data_Costs!$C$220:$C$299,Data_Costs!$B$220:$B$299,"B2C",Data_Costs!$A$220:$A$299,">="&Assumptions!$B$15,Data_Costs!$A$220:$A$299,"<="&Assumptions!$B$13) | F28: =$B$10*B28/$B$6 | G28: =$C$10*C28/$C$6 | H28: =(B28+F28)/D28 | I28: =(C28+G28)/E28 | J28: =$E$22 | K28: =$B$24 | L28: =SUMIFS(Data_MRR!$H$5:$H$84,Data_MRR!$B$5:$B$84,"B2C",Data_MRR!$A$5:$A$84,Assumptions!$B$10) | M28: =C94 | N28: =J28*K28*M28 | O28: =N28/H28
A29: SMB | B29: =SUMIFS(Data_Costs!$D$6:$D$149,Data_Costs!$B$6:$B$149,"SMB",Data_Costs!$A$6:$A$149,">="&Assumptions!$B$12,Data_Costs!$A$6:$A$149,"<="&Assumptions!$B$13) | C29: =SUMIFS(Data_Costs!$D$6:$D$149,Data_Costs!$B$6:$B$149,"SMB",Data_Costs!$A$6:$A$149,">="&Assumptions!$B$15,Data_Costs!$A$6:$A$149,"<="&Assumptions!$B$13) | D29: =SUMIFS(Data_Costs!$C$220:$C$299,Data_Costs!$B$220:$B$299,"SMB",Data_Costs!$A$220:$A$299,">="&Assumptions!$B$12,Data_Costs!$A$220:$A$299,"<="&Assumptions!$B$13) | E29: =SUMIFS(Data_Costs!$C$220:$C$299,Data_Costs!$B$220:$B$299,"SMB",Data_Costs!$A$220:$A$299,">="&Assumptions!$B$15,Data_Costs!$A$220:$A$299,"<="&Assumptions!$B$13) | F29: =$B$10*B29/$B$6 | G29: =$C$10*C29/$C$6 | H29: =(B29+F29)/D29 | I29: =(C29+G29)/E29 | J29: =$F$22 | K29: =$B$24 | L29: =SUMIFS(Data_MRR!$H$5:$H$84,Data_MRR!$B$5:$B$84,"SMB",Data_MRR!$A$5:$A$84,Assumptions!$B$10) | M29: =F94 | N29: =J29*K29*M29 | O29: =N29/H29
A30: Enterprise | B30: =SUMIFS(Data_Costs!$D$6:$D$149,Data_Costs!$B$6:$B$149,"Enterprise",Data_Costs!$A$6:$A$149,">="&Assumptions!$B$12,Data_Costs!$A$6:$A$149,"<="&Assumptions!$B$13) | C30: =SUMIFS(Data_Costs!$D$6:$D$149,Data_Costs!$B$6:$B$149,"Enterprise",Data_Costs!$A$6:$A$149,">="&Assumptions!$B$15,Data_Costs!$A$6:$A$149,"<="&Assumptions!$B$13) | D30: =SUMIFS(Data_Costs!$C$220:$C$299,Data_Costs!$B$220:$B$299,"Enterprise",Data_Costs!$A$220:$A$299,">="&Assumptions!$B$12,Data_Costs!$A$220:$A$299,"<="&Assumptions!$B$13) | E30: =SUMIFS(Data_Costs!$C$220:$C$299,Data_Costs!$B$220:$B$299,"Enterprise",Data_Costs!$A$220:$A$299,">="&Assumptions!$B$15,Data_Costs!$A$220:$A$299,"<="&Assumptions!$B$13) | F30: =$B$10*B30/$B$6 | G30: =$C$10*C30/$C$6 | H30: =(B30+F30)/D30 | I30: =(C30+G30)/E30 | J30: =$G$22 | K30: =$B$24 | L30: =SUMIFS(Data_MRR!$H$5:$H$84,Data_MRR!$B$5:$B$84,"Enterprise",Data_MRR!$A$5:$A$84,Assumptions!$B$10) | M30: =I94 | N30: =J30*K30*M30 | O30: =N30/H30
A31: Total | B31: =SUM(B28:B30) | C31: =SUM(C28:C30) | D31: =SUM(D28:D30) | E31: =SUM(E28:E30) | F31: =$B$10*B31/$B$6 | G31: =$C$10*C31/$C$6 | H31: =(B31+F31)/D31 | I31: =(C31+G31)/E31 | J31: =AVERAGE(E22:G22) | K31: =$B$24 | L31: =SUMIFS(Data_MRR!$H$5:$H$84,Data_MRR!$B$5:$B$84,"Total",Data_MRR!$A$5:$A$84,Assumptions!$B$10) | M31: =SUMPRODUCT(D28:D30,M28:M30)/D31 | N31: =SUMPRODUCT(D28:D30,N28:N30)/D31 | O31: =N31/H31
A33: 60-month lifetime curve, $ basis (M-14; A-15..A-18, A-23): observed dollar retention for k=0..k_rel (Data_Survival), then an extrapolated geometric tail using each segment's tail decay rate (Assumptions). Lifetime = sum of the curve.
A34: k (months since signup) | B34: B2C curve | C34: B2C cumulative (=lifetime thru k) | D34: B2C cum. gross profit/cust | E34: SMB curve | F34: SMB cumulative (=lifetime thru k) | G34: SMB cum. gross profit/cust | H34: Enterprise curve | I34: Enterprise cumulative (=lifetime thru k) | J34: Enterprise cum. gross profit/cust
A35: 0 | B35: =SUMIFS(Data_Survival!$H$5:$H$84,Data_Survival!$A$5:$A$84,"B2C",Data_Survival!$B$5:$B$84,$A35) | C35: =B35 | D35: =C35*$E$22*$B$24 | E35: =SUMIFS(Data_Survival!$H$5:$H$84,Data_Survival!$A$5:$A$84,"SMB",Data_Survival!$B$5:$B$84,$A35) | F35: =E35 | G35: =F35*$F$22*$B$24 | H35: =SUMIFS(Data_Survival!$H$5:$H$84,Data_Survival!$A$5:$A$84,"Enterprise",Data_Survival!$B$5:$B$84,$A35) | I35: =H35 | J35: =I35*$G$22*$B$24
A36: 1 | B36: =IF($A36<=Assumptions!$B$44,SUMIFS(Data_Survival!$H$5:$H$84,Data_Survival!$A$5:$A$84,"B2C",Data_Survival!$B$5:$B$84,$A36),B35*(1-Assumptions!$C$44)) | C36: =C35+B36 | D36: =C36*$E$22*$B$24 | E36: =IF($A36<=Assumptions!$B$45,SUMIFS(Data_Survival!$H$5:$H$84,Data_Survival!$A$5:$A$84,"SMB",Data_Survival!$B$5:$B$84,$A36),E35*(1-Assumptions!$C$45)) | F36: =F35+E36 | G36: =F36*$F$22*$B$24 | H36: =IF($A36<=Assumptions!$B$46,SUMIFS(Data_Survival!$H$5:$H$84,Data_Survival!$A$5:$A$84,"Enterprise",Data_Survival!$B$5:$B$84,$A36),H35*(1-Assumptions!$C$46)) | I36: =I35+H36 | J36: =I36*$G$22*$B$24
A37: 2 | B37: =IF($A37<=Assumptions!$B$44,SUMIFS(Data_Survival!$H$5:$H$84,Data_Survival!$A$5:$A$84,"B2C",Data_Survival!$B$5:$B$84,$A37),B36*(1-Assumptions!$C$44)) | C37: =C36+B37 | D37: =C37*$E$22*$B$24 | E37: =IF($A37<=Assumptions!$B$45,SUMIFS(Data_Survival!$H$5:$H$84,Data_Survival!$A$5:$A$84,"SMB",Data_Survival!$B$5:$B$84,$A37),E36*(1-Assumptions!$C$45)) | F37: =F36+E37 | G37: =F37*$F$22*$B$24 | H37: =IF($A37<=Assumptions!$B$46,SUMIFS(Data_Survival!$H$5:$H$84,Data_Survival!$A$5:$A$84,"Enterprise",Data_Survival!$B$5:$B$84,$A37),H36*(1-Assumptions!$C$46)) | I37: =I36+H37 | J37: =I37*$G$22*$B$24
A38: 3 | B38: =IF($A38<=Assumptions!$B$44,SUMIFS(Data_Survival!$H$5:$H$84,Data_Survival!$A$5:$A$84,"B2C",Data_Survival!$B$5:$B$84,$A38),B37*(1-Assumptions!$C$44)) | C38: =C37+B38 | D38: =C38*$E$22*$B$24 | E38: =IF($A38<=Assumptions!$B$45,SUMIFS(Data_Survival!$H$5:$H$84,Data_Survival!$A$5:$A$84,"SMB",Data_Survival!$B$5:$B$84,$A38),E37*(1-Assumptions!$C$45)) | F38: =F37+E38 | G38: =F38*$F$22*$B$24 | H38: =IF($A38<=Assumptions!$B$46,SUMIFS(Data_Survival!$H$5:$H$84,Data_Survival!$A$5:$A$84,"Enterprise",Data_Survival!$B$5:$B$84,$A38),H37*(1-Assumptions!$C$46)) | I38: =I37+H38 | J38: =I38*$G$22*$B$24
A39: 4 | B39: =IF($A39<=Assumptions!$B$44,SUMIFS(Data_Survival!$H$5:$H$84,Data_Survival!$A$5:$A$84,"B2C",Data_Survival!$B$5:$B$84,$A39),B38*(1-Assumptions!$C$44)) | C39: =C38+B39 | D39: =C39*$E$22*$B$24 | E39: =IF($A39<=Assumptions!$B$45,SUMIFS(Data_Survival!$H$5:$H$84,Data_Survival!$A$5:$A$84,"SMB",Data_Survival!$B$5:$B$84,$A39),E38*(1-Assumptions!$C$45)) | F39: =F38+E39 | G39: =F39*$F$22*$B$24 | H39: =IF($A39<=Assumptions!$B$46,SUMIFS(Data_Survival!$H$5:$H$84,Data_Survival!$A$5:$A$84,"Enterprise",Data_Survival!$B$5:$B$84,$A39),H38*(1-Assumptions!$C$46)) | I39: =I38+H39 | J39: =I39*$G$22*$B$24
A40: 5 | B40: =IF($A40<=Assumptions!$B$44,SUMIFS(Data_Survival!$H$5:$H$84,Data_Survival!$A$5:$A$84,"B2C",Data_Survival!$B$5:$B$84,$A40),B39*(1-Assumptions!$C$44)) | C40: =C39+B40 | D40: =C40*$E$22*$B$24 | E40: =IF($A40<=Assumptions!$B$45,SUMIFS(Data_Survival!$H$5:$H$84,Data_Survival!$A$5:$A$84,"SMB",Data_Survival!$B$5:$B$84,$A40),E39*(1-Assumptions!$C$45)) | F40: =F39+E40 | G40: =F40*$F$22*$B$24 | H40: =IF($A40<=Assumptions!$B$46,SUMIFS(Data_Survival!$H$5:$H$84,Data_Survival!$A$5:$A$84,"Enterprise",Data_Survival!$B$5:$B$84,$A40),H39*(1-Assumptions!$C$46)) | I40: =I39+H40 | J40: =I40*$G$22*$B$24
A41: 6 | B41: =IF($A41<=Assumptions!$B$44,SUMIFS(Data_Survival!$H$5:$H$84,Data_Survival!$A$5:$A$84,"B2C",Data_Survival!$B$5:$B$84,$A41),B40*(1-Assumptions!$C$44)) | C41: =C40+B41 | D41: =C41*$E$22*$B$24 | E41: =IF($A41<=Assumptions!$B$45,SUMIFS(Data_Survival!$H$5:$H$84,Data_Survival!$A$5:$A$84,"SMB",Data_Survival!$B$5:$B$84,$A41),E40*(1-Assumptions!$C$45)) | F41: =F40+E41 | G41: =F41*$F$22*$B$24 | H41: =IF($A41<=Assumptions!$B$46,SUMIFS(Data_Survival!$H$5:$H$84,Data_Survival!$A$5:$A$84,"Enterprise",Data_Survival!$B$5:$B$84,$A41),H40*(1-Assumptions!$C$46)) | I41: =I40+H41 | J41: =I41*$G$22*$B$24
A42: 7 | B42: =IF($A42<=Assumptions!$B$44,SUMIFS(Data_Survival!$H$5:$H$84,Data_Survival!$A$5:$A$84,"B2C",Data_Survival!$B$5:$B$84,$A42),B41*(1-Assumptions!$C$44)) | C42: =C41+B42 | D42: =C42*$E$22*$B$24 | E42: =IF($A42<=Assumptions!$B$45,SUMIFS(Data_Survival!$H$5:$H$84,Data_Survival!$A$5:$A$84,"SMB",Data_Survival!$B$5:$B$84,$A42),E41*(1-Assumptions!$C$45)) | F42: =F41+E42 | G42: =F42*$F$22*$B$24 | H42: =IF($A42<=Assumptions!$B$46,SUMIFS(Data_Survival!$H$5:$H$84,Data_Survival!$A$5:$A$84,"Enterprise",Data_Survival!$B$5:$B$84,$A42),H41*(1-Assumptions!$C$46)) | I42: =I41+H42 | J42: =I42*$G$22*$B$24
A43: 8 | B43: =IF($A43<=Assumptions!$B$44,SUMIFS(Data_Survival!$H$5:$H$84,Data_Survival!$A$5:$A$84,"B2C",Data_Survival!$B$5:$B$84,$A43),B42*(1-Assumptions!$C$44)) | C43: =C42+B43 | D43: =C43*$E$22*$B$24 | E43: =IF($A43<=Assumptions!$B$45,SUMIFS(Data_Survival!$H$5:$H$84,Data_Survival!$A$5:$A$84,"SMB",Data_Survival!$B$5:$B$84,$A43),E42*(1-Assumptions!$C$45)) | F43: =F42+E43 | G43: =F43*$F$22*$B$24 | H43: =IF($A43<=Assumptions!$B$46,SUMIFS(Data_Survival!$H$5:$H$84,Data_Survival!$A$5:$A$84,"Enterprise",Data_Survival!$B$5:$B$84,$A43),H42*(1-Assumptions!$C$46)) | I43: =I42+H43 | J43: =I43*$G$22*$B$24
A44: 9 | B44: =IF($A44<=Assumptions!$B$44,SUMIFS(Data_Survival!$H$5:$H$84,Data_Survival!$A$5:$A$84,"B2C",Data_Survival!$B$5:$B$84,$A44),B43*(1-Assumptions!$C$44)) | C44: =C43+B44 | D44: =C44*$E$22*$B$24 | E44: =IF($A44<=Assumptions!$B$45,SUMIFS(Data_Survival!$H$5:$H$84,Data_Survival!$A$5:$A$84,"SMB",Data_Survival!$B$5:$B$84,$A44),E43*(1-Assumptions!$C$45)) | F44: =F43+E44 | G44: =F44*$F$22*$B$24 | H44: =IF($A44<=Assumptions!$B$46,SUMIFS(Data_Survival!$H$5:$H$84,Data_Survival!$A$5:$A$84,"Enterprise",Data_Survival!$B$5:$B$84,$A44),H43*(1-Assumptions!$C$46)) | I44: =I43+H44 | J44: =I44*$G$22*$B$24
A45: 10 | B45: =IF($A45<=Assumptions!$B$44,SUMIFS(Data_Survival!$H$5:$H$84,Data_Survival!$A$5:$A$84,"B2C",Data_Survival!$B$5:$B$84,$A45),B44*(1-Assumptions!$C$44)) | C45: =C44+B45 | D45: =C45*$E$22*$B$24 | E45: =IF($A45<=Assumptions!$B$45,SUMIFS(Data_Survival!$H$5:$H$84,Data_Survival!$A$5:$A$84,"SMB",Data_Survival!$B$5:$B$84,$A45),E44*(1-Assumptions!$C$45)) | F45: =F44+E45 | G45: =F45*$F$22*$B$24 | H45: =IF($A45<=Assumptions!$B$46,SUMIFS(Data_Survival!$H$5:$H$84,Data_Survival!$A$5:$A$84,"Enterprise",Data_Survival!$B$5:$B$84,$A45),H44*(1-Assumptions!$C$46)) | I45: =I44+H45 | J45: =I45*$G$22*$B$24
A46: 11 | B46: =IF($A46<=Assumptions!$B$44,SUMIFS(Data_Survival!$H$5:$H$84,Data_Survival!$A$5:$A$84,"B2C",Data_Survival!$B$5:$B$84,$A46),B45*(1-Assumptions!$C$44)) | C46: =C45+B46 | D46: =C46*$E$22*$B$24 | E46: =IF($A46<=Assumptions!$B$45,SUMIFS(Data_Survival!$H$5:$H$84,Data_Survival!$A$5:$A$84,"SMB",Data_Survival!$B$5:$B$84,$A46),E45*(1-Assumptions!$C$45)) | F46: =F45+E46 | G46: =F46*$F$22*$B$24 | H46: =IF($A46<=Assumptions!$B$46,SUMIFS(Data_Survival!$H$5:$H$84,Data_Survival!$A$5:$A$84,"Enterprise",Data_Survival!$B$5:$B$84,$A46),H45*(1-Assumptions!$C$46)) | I46: =I45+H46 | J46: =I46*$G$22*$B$24
A47: 12 | B47: =IF($A47<=Assumptions!$B$44,SUMIFS(Data_Survival!$H$5:$H$84,Data_Survival!$A$5:$A$84,"B2C",Data_Survival!$B$5:$B$84,$A47),B46*(1-Assumptions!$C$44)) | C47: =C46+B47 | D47: =C47*$E$22*$B$24 | E47: =IF($A47<=Assumptions!$B$45,SUMIFS(Data_Survival!$H$5:$H$84,Data_Survival!$A$5:$A$84,"SMB",Data_Survival!$B$5:$B$84,$A47),E46*(1-Assumptions!$C$45)) | F47: =F46+E47 | G47: =F47*$F$22*$B$24 | H47: =IF($A47<=Assumptions!$B$46,SUMIFS(Data_Survival!$H$5:$H$84,Data_Survival!$A$5:$A$84,"Enterprise",Data_Survival!$B$5:$B$84,$A47),H46*(1-Assumptions!$C$46)) | I47: =I46+H47 | J47: =I47*$G$22*$B$24
... A94: 59 | B94: =IF($A94<=Assumptions!$B$44,SUMIFS(Data_Survival!$H$5:$H$84,Data_Survival!$A$5:$A$84,"B2C",Data_Survival!$B$5:$B$84,$A94),B93*(1-Assumptions!$C$44)) | C94: =C93+B94 | D94: =C94*$E$22*$B$24 | E94: =IF($A94<=Assumptions!$B$45,SUMIFS(Data_Survival!$H$5:$H$84,Data_Survival!$A$5:$A$84,"SMB",Data_Survival!$B$5:$B$84,$A94),E93*(1-Assumptions!$C$45)) | F94: =F93+E94 | G94: =F94*$F$22*$B$24 | H94: =IF($A94<=Assumptions!$B$46,SUMIFS(Data_Survival!$H$5:$H$84,Data_Survival!$A$5:$A$84,"Enterprise",Data_Survival!$B$5:$B$84,$A94),H93*(1-Assumptions!$C$46)) | I94: =I93+H94 | J94: =I94*$G$22*$B$24
A96: CAC payback & retention-adjusted payback (M-15; resolves the WP40 open issue -- computed on the full extrapolated 60-month curve, not just the observed horizon)
A97: Segment | B97: CAC payback = CAC / (ARPA x GM%), months | C97: Retention-adjusted payback (first month cum. gross profit/customer >= CAC; '> 60' if never)
A98: B2C | B98: =H28/(J28*K28) | C98: =IF(SUMPRODUCT((D35:D94<$H$28)*1)=60,"> 60",SUMPRODUCT((D35:D94<$H$28)*1)+1)
A99: SMB | B99: =H29/(J29*K29) | C99: =IF(SUMPRODUCT((G35:G94<$H$29)*1)=60,"> 60",SUMPRODUCT((G35:G94<$H$29)*1)+1)
A100: Enterprise | B100: =H30/(J30*K30) | C100: =IF(SUMPRODUCT((J35:J94<$H$30)*1)=60,"> 60",SUMPRODUCT((J35:J94<$H$30)*1)+1)
A101: Total | B101: =H31/(J31*K31) | C101: ="n/a (company blend)"
A103: Sensitivity grid: LTV by GM basis x lifetime cap (36 / 60 months) -- formulas only, no data tables
A104: Segment | B104: T6M avg GM% x 36mo cap | C104: T6M avg GM% x 60mo cap | D104: Apr-24 run-rate GM% x 36mo cap | E104: Apr-24 run-rate GM% x 60mo cap
A105: B2C | B105: =$E$22*$D$20*C70 | C105: =$E$22*$D$20*C94 | D105: =$E$22*$D$21*C70 | E105: =$E$22*$D$21*C94
A106: SMB | B106: =$F$22*$D$20*F70 | C106: =$F$22*$D$20*F94 | D106: =$F$22*$D$21*F70 | E106: =$F$22*$D$21*F94
A107: Enterprise | B107: =$G$22*$D$20*I70 | C107: =$G$22*$D$20*I94 | D107: =$G$22*$D$21*I70 | E107: =$G$22*$D$21*I94

Sheet Scenarios
A1: Scenarios
A2: A simplified, formula-driven 12-month (May-24..Apr-25) projection by segment, in three parallel Base/Bull/Bear blocks (no selector needed -- all three are always computed). Simplification vs. the Python engine (sql/python_models/scenarios.py): this sheet tracks ONE bucket per segment (not per plan_type), blends monthly/annual rates using the Apr-24 stock mix (churn) and the T6M new-customer plan mix (ARPA) held constant for the whole horizon, and does not model the B2C monthly->annual migration lever. See the reconciliation block at the bottom (target <= 3% gap on Apr-25 total MRR).
A4: Blended driver build (per segment): stock-mix-weighted churn, new-customer-mix ARPA blend, and the Base/Bull/Bear variant of each rate -- all linked to Assumptions (no hard-coded numbers)
A5: Segment | B5: Stock share, monthly (Apr-24) | C5: Stock share, annual (Apr-24) | D5: Churn blend, Base | E5: Churn blend, Bull | F5: Churn blend, Bear | G5: New-cust ARPA blend | H5: Expansion, Base | I5: Expansion, Bull | J5: Expansion, Bear | K5: Contraction, Base | L5: Contraction, Bull | M5: Contraction, Bear | N5: New customers/mo, Base | O5: Trend slope/mo (Bull)
A6: B2C | B6: =SUMIFS(Assumptions!$C$29:$C$34,Assumptions!$A$29:$A$34,"B2C",Assumptions!$B$29:$B$34,"monthly")/(SUMIFS(Assumptions!$C$29:$C$34,Assumptions!$A$29:$A$34,"B2C",Assumptions!$B$29:$B$34,"monthly")+SUMIFS(Assumptions!$C$29:$C$34,Assumptions!$A$29:$A$34,"B2C",Assumptions!$B$29:$B$34,"annual")) | C6: =1-B6 | D6: =B6*Assumptions!$B$57+C6*Assumptions!$B$58 | E6: =B6*Assumptions!$B$57*(1-Assumptions!$B$71)+C6*Assumptions!$B$58 | F6: =D6*(1+Assumptions!$B$65) | G6: =Assumptions!$B$55*Assumptions!$B$53+Assumptions!$B$56*Assumptions!$B$54 | H6: =Assumptions!$B$59 | I6: =Assumptions!$B$59 | J6: =Assumptions!$B$59 | K6: =Assumptions!$B$60 | L6: =Assumptions!$B$60 | M6: =Assumptions!$B$60 | N6: =Assumptions!$B$51 | O6: =Assumptions!$B$52
A7: SMB | B7: =SUMIFS(Assumptions!$C$29:$C$34,Assumptions!$A$29:$A$34,"SMB",Assumptions!$B$29:$B$34,"monthly")/(SUMIFS(Assumptions!$C$29:$C$34,Assumptions!$A$29:$A$34,"SMB",Assumptions!$B$29:$B$34,"monthly")+SUMIFS(Assumptions!$C$29:$C$34,Assumptions!$A$29:$A$34,"SMB",Assumptions!$B$29:$B$34,"annual")) | C7: =1-B7 | D7: =B7*Assumptions!$C$57+C7*Assumptions!$C$58 | E7: =B7*Assumptions!$C$57*(1-Assumptions!$B$71)+C7*Assumptions!$C$58 | F7: =D7*(1+Assumptions!$B$65) | G7: =Assumptions!$C$55*Assumptions!$C$53+Assumptions!$C$56*Assumptions!$C$54 | H7: =Assumptions!$C$59 | I7: =Assumptions!$C$59*(1+Assumptions!$B$73) | J7: =Assumptions!$C$59*Assumptions!$B$66 | K7: =Assumptions!$C$60 | L7: =Assumptions!$C$60 | M7: =Assumptions!$C$60 | N7: =Assumptions!$C$51 | O7: =Assumptions!$C$52
A8: Enterprise | B8: =SUMIFS(Assumptions!$C$29:$C$34,Assumptions!$A$29:$A$34,"Enterprise",Assumptions!$B$29:$B$34,"monthly")/(SUMIFS(Assumptions!$C$29:$C$34,Assumptions!$A$29:$A$34,"Enterprise",Assumptions!$B$29:$B$34,"monthly")+SUMIFS(Assumptions!$C$29:$C$34,Assumptions!$A$29:$A$34,"Enterprise",Assumptions!$B$29:$B$34,"annual")) | C8: =1-B8 | D8: =B8*Assumptions!$D$57+C8*Assumptions!$D$58 | E8: =B8*Assumptions!$D$57*(1-Assumptions!$B$71)+C8*Assumptions!$D$58 | F8: =D8*(1+Assumptions!$B$65) | G8: =Assumptions!$D$55*Assumptions!$D$53+Assumptions!$D$56*Assumptions!$D$54 | H8: =Assumptions!$D$59 | I8: =Assumptions!$D$59 | J8: =Assumptions!$D$59*Assumptions!$B$67 | K8: =Assumptions!$D$60 | L8: =Assumptions!$D$60*(1-Assumptions!$B$74) | M8: =Assumptions!$D$60 | N8: =Assumptions!$D$51 | O8: =Assumptions!$D$52
A10: Scenario: Base -- 12-month projection by segment (May-24..Apr-25)
A11: Base / B2C
A12: Month # | B12: Opening customers | C12: New customers | D12: Churn customers | E12: Closing customers | F12: Opening MRR | G12: New MRR | H12: Expansion MRR | I12: Contraction MRR | J12: Churn MRR | K12: Closing MRR
A13: 1 | B13: =SUMIFS(Data_MRR!$I:$I,Data_MRR!$B:$B,"B2C",Data_MRR!$A:$A,Assumptions!$B$10) | C13: =$N$6 | D13: =B13*$D$6 | E13: =B13-D13+C13 | F13: =SUMIFS(Data_MRR!$H:$H,Data_MRR!$B:$B,"B2C",Data_MRR!$A:$A,Assumptions!$B$10) | G13: =C13*$G$6 | H13: =F13*$H$6 | I13: =F13*$K$6 | J13: =F13*$D$6 | K13: =F13-J13+G13+H13-I13
A14: 2 | B14: =E13 | C14: =$N$6 | D14: =B14*$D$6 | E14: =B14-D14+C14 | F14: =K13 | G14: =C14*$G$6 | H14: =F14*$H$6 | I14: =F14*$K$6 | J14: =F14*$D$6 | K14: =F14-J14+G14+H14-I14
A15: 3 | B15: =E14 | C15: =$N$6 | D15: =B15*$D$6 | E15: =B15-D15+C15 | F15: =K14 | G15: =C15*$G$6 | H15: =F15*$H$6 | I15: =F15*$K$6 | J15: =F15*$D$6 | K15: =F15-J15+G15+H15-I15
A16: 4 | B16: =E15 | C16: =$N$6 | D16: =B16*$D$6 | E16: =B16-D16+C16 | F16: =K15 | G16: =C16*$G$6 | H16: =F16*$H$6 | I16: =F16*$K$6 | J16: =F16*$D$6 | K16: =F16-J16+G16+H16-I16
A17: 5 | B17: =E16 | C17: =$N$6 | D17: =B17*$D$6 | E17: =B17-D17+C17 | F17: =K16 | G17: =C17*$G$6 | H17: =F17*$H$6 | I17: =F17*$K$6 | J17: =F17*$D$6 | K17: =F17-J17+G17+H17-I17
A18: 6 | B18: =E17 | C18: =$N$6 | D18: =B18*$D$6 | E18: =B18-D18+C18 | F18: =K17 | G18: =C18*$G$6 | H18: =F18*$H$6 | I18: =F18*$K$6 | J18: =F18*$D$6 | K18: =F18-J18+G18+H18-I18
A19: 7 | B19: =E18 | C19: =$N$6 | D19: =B19*$D$6 | E19: =B19-D19+C19 | F19: =K18 | G19: =C19*$G$6 | H19: =F19*$H$6 | I19: =F19*$K$6 | J19: =F19*$D$6 | K19: =F19-J19+G19+H19-I19
A20: 8 | B20: =E19 | C20: =$N$6 | D20: =B20*$D$6 | E20: =B20-D20+C20 | F20: =K19 | G20: =C20*$G$6 | H20: =F20*$H$6 | I20: =F20*$K$6 | J20: =F20*$D$6 | K20: =F20-J20+G20+H20-I20
A21: 9 | B21: =E20 | C21: =$N$6 | D21: =B21*$D$6 | E21: =B21-D21+C21 | F21: =K20 | G21: =C21*$G$6 | H21: =F21*$H$6 | I21: =F21*$K$6 | J21: =F21*$D$6 | K21: =F21-J21+G21+H21-I21
A22: 10 | B22: =E21 | C22: =$N$6 | D22: =B22*$D$6 | E22: =B22-D22+C22 | F22: =K21 | G22: =C22*$G$6 | H22: =F22*$H$6 | I22: =F22*$K$6 | J22: =F22*$D$6 | K22: =F22-J22+G22+H22-I22
A23: 11 | B23: =E22 | C23: =$N$6 | D23: =B23*$D$6 | E23: =B23-D23+C23 | F23: =K22 | G23: =C23*$G$6 | H23: =F23*$H$6 | I23: =F23*$K$6 | J23: =F23*$D$6 | K23: =F23-J23+G23+H23-I23
A24: 12 | B24: =E23 | C24: =$N$6 | D24: =B24*$D$6 | E24: =B24-D24+C24 | F24: =K23 | G24: =C24*$G$6 | H24: =F24*$H$6 | I24: =F24*$K$6 | J24: =F24*$D$6 | K24: =F24-J24+G24+H24-I24
A26: Base / SMB
A27: Month # | B27: Opening customers | C27: New customers | D27: Churn customers | E27: Closing customers | F27: Opening MRR | G27: New MRR | H27: Expansion MRR | I27: Contraction MRR | J27: Churn MRR | K27: Closing MRR
A28: 1 | B28: =SUMIFS(Data_MRR!$I:$I,Data_MRR!$B:$B,"SMB",Data_MRR!$A:$A,Assumptions!$B$10) | C28: =$N$7 | D28: =B28*$D$7 | E28: =B28-D28+C28 | F28: =SUMIFS(Data_MRR!$H:$H,Data_MRR!$B:$B,"SMB",Data_MRR!$A:$A,Assumptions!$B$10) | G28: =C28*$G$7 | H28: =F28*$H$7 | I28: =F28*$K$7 | J28: =F28*$D$7 | K28: =F28-J28+G28+H28-I28
A29: 2 | B29: =E28 | C29: =$N$7 | D29: =B29*$D$7 | E29: =B29-D29+C29 | F29: =K28 | G29: =C29*$G$7 | H29: =F29*$H$7 | I29: =F29*$K$7 | J29: =F29*$D$7 | K29: =F29-J29+G29+H29-I29
A30: 3 | B30: =E29 | C30: =$N$7 | D30: =B30*$D$7 | E30: =B30-D30+C30 | F30: =K29 | G30: =C30*$G$7 | H30: =F30*$H$7 | I30: =F30*$K$7 | J30: =F30*$D$7 | K30: =F30-J30+G30+H30-I30
A31: 4 | B31: =E30 | C31: =$N$7 | D31: =B31*$D$7 | E31: =B31-D31+C31 | F31: =K30 | G31: =C31*$G$7 | H31: =F31*$H$7 | I31: =F31*$K$7 | J31: =F31*$D$7 | K31: =F31-J31+G31+H31-I31
A32: 5 | B32: =E31 | C32: =$N$7 | D32: =B32*$D$7 | E32: =B32-D32+C32 | F32: =K31 | G32: =C32*$G$7 | H32: =F32*$H$7 | I32: =F32*$K$7 | J32: =F32*$D$7 | K32: =F32-J32+G32+H32-I32
A33: 6 | B33: =E32 | C33: =$N$7 | D33: =B33*$D$7 | E33: =B33-D33+C33 | F33: =K32 | G33: =C33*$G$7 | H33: =F33*$H$7 | I33: =F33*$K$7 | J33: =F33*$D$7 | K33: =F33-J33+G33+H33-I33
A34: 7 | B34: =E33 | C34: =$N$7 | D34: =B34*$D$7 | E34: =B34-D34+C34 | F34: =K33 | G34: =C34*$G$7 | H34: =F34*$H$7 | I34: =F34*$K$7 | J34: =F34*$D$7 | K34: =F34-J34+G34+H34-I34
A35: 8 | B35: =E34 | C35: =$N$7 | D35: =B35*$D$7 | E35: =B35-D35+C35 | F35: =K34 | G35: =C35*$G$7 | H35: =F35*$H$7 | I35: =F35*$K$7 | J35: =F35*$D$7 | K35: =F35-J35+G35+H35-I35
A36: 9 | B36: =E35 | C36: =$N$7 | D36: =B36*$D$7 | E36: =B36-D36+C36 | F36: =K35 | G36: =C36*$G$7 | H36: =F36*$H$7 | I36: =F36*$K$7 | J36: =F36*$D$7 | K36: =F36-J36+G36+H36-I36
A37: 10 | B37: =E36 | C37: =$N$7 | D37: =B37*$D$7 | E37: =B37-D37+C37 | F37: =K36 | G37: =C37*$G$7 | H37: =F37*$H$7 | I37: =F37*$K$7 | J37: =F37*$D$7 | K37: =F37-J37+G37+H37-I37
A38: 11 | B38: =E37 | C38: =$N$7 | D38: =B38*$D$7 | E38: =B38-D38+C38 | F38: =K37 | G38: =C38*$G$7 | H38: =F38*$H$7 | I38: =F38*$K$7 | J38: =F38*$D$7 | K38: =F38-J38+G38+H38-I38
A39: 12 | B39: =E38 | C39: =$N$7 | D39: =B39*$D$7 | E39: =B39-D39+C39 | F39: =K38 | G39: =C39*$G$7 | H39: =F39*$H$7 | I39: =F39*$K$7 | J39: =F39*$D$7 | K39: =F39-J39+G39+H39-I39
A41: Base / Enterprise
A42: Month # | B42: Opening customers | C42: New customers | D42: Churn customers | E42: Closing customers | F42: Opening MRR | G42: New MRR | H42: Expansion MRR | I42: Contraction MRR | J42: Churn MRR | K42: Closing MRR
A43: 1 | B43: =SUMIFS(Data_MRR!$I:$I,Data_MRR!$B:$B,"Enterprise",Data_MRR!$A:$A,Assumptions!$B$10) | C43: =$N$8 | D43: =B43*$D$8 | E43: =B43-D43+C43 | F43: =SUMIFS(Data_MRR!$H:$H,Data_MRR!$B:$B,"Enterprise",Data_MRR!$A:$A,Assumptions!$B$10) | G43: =C43*$G$8 | H43: =F43*$H$8 | I43: =F43*$K$8 | J43: =F43*$D$8 | K43: =F43-J43+G43+H43-I43
A44: 2 | B44: =E43 | C44: =$N$8 | D44: =B44*$D$8 | E44: =B44-D44+C44 | F44: =K43 | G44: =C44*$G$8 | H44: =F44*$H$8 | I44: =F44*$K$8 | J44: =F44*$D$8 | K44: =F44-J44+G44+H44-I44
A45: 3 | B45: =E44 | C45: =$N$8 | D45: =B45*$D$8 | E45: =B45-D45+C45 | F45: =K44 | G45: =C45*$G$8 | H45: =F45*$H$8 | I45: =F45*$K$8 | J45: =F45*$D$8 | K45: =F45-J45+G45+H45-I45
A46: 4 | B46: =E45 | C46: =$N$8 | D46: =B46*$D$8 | E46: =B46-D46+C46 | F46: =K45 | G46: =C46*$G$8 | H46: =F46*$H$8 | I46: =F46*$K$8 | J46: =F46*$D$8 | K46: =F46-J46+G46+H46-I46
A47: 5 | B47: =E46 | C47: =$N$8 | D47: =B47*$D$8 | E47: =B47-D47+C47 | F47: =K46 | G47: =C47*$G$8 | H47: =F47*$H$8 | I47: =F47*$K$8 | J47: =F47*$D$8 | K47: =F47-J47+G47+H47-I47
A48: 6 | B48: =E47 | C48: =$N$8 | D48: =B48*$D$8 | E48: =B48-D48+C48 | F48: =K47 | G48: =C48*$G$8 | H48: =F48*$H$8 | I48: =F48*$K$8 | J48: =F48*$D$8 | K48: =F48-J48+G48+H48-I48
A49: 7 | B49: =E48 | C49: =$N$8 | D49: =B49*$D$8 | E49: =B49-D49+C49 | F49: =K48 | G49: =C49*$G$8 | H49: =F49*$H$8 | I49: =F49*$K$8 | J49: =F49*$D$8 | K49: =F49-J49+G49+H49-I49
A50: 8 | B50: =E49 | C50: =$N$8 | D50: =B50*$D$8 | E50: =B50-D50+C50 | F50: =K49 | G50: =C50*$G$8 | H50: =F50*$H$8 | I50: =F50*$K$8 | J50: =F50*$D$8 | K50: =F50-J50+G50+H50-I50
A51: 9 | B51: =E50 | C51: =$N$8 | D51: =B51*$D$8 | E51: =B51-D51+C51 | F51: =K50 | G51: =C51*$G$8 | H51: =F51*$H$8 | I51: =F51*$K$8 | J51: =F51*$D$8 | K51: =F51-J51+G51+H51-I51
A52: 10 | B52: =E51 | C52: =$N$8 | D52: =B52*$D$8 | E52: =B52-D52+C52 | F52: =K51 | G52: =C52*$G$8 | H52: =F52*$H$8 | I52: =F52*$K$8 | J52: =F52*$D$8 | K52: =F52-J52+G52+H52-I52
A53: 11 | B53: =E52 | C53: =$N$8 | D53: =B53*$D$8 | E53: =B53-D53+C53 | F53: =K52 | G53: =C53*$G$8 | H53: =F53*$H$8 | I53: =F53*$K$8 | J53: =F53*$D$8 | K53: =F53-J53+G53+H53-I53
A54: 12 | B54: =E53 | C54: =$N$8 | D54: =B54*$D$8 | E54: =B54-D54+C54 | F54: =K53 | G54: =C54*$G$8 | H54: =F54*$H$8 | I54: =F54*$K$8 | J54: =F54*$D$8 | K54: =F54-J54+G54+H54-I54
A57: Scenario: Bull -- 12-month projection by segment (May-24..Apr-25)
A58: Bull / B2C
A59: Month # | B59: Opening customers | C59: New customers | D59: Churn customers | E59: Closing customers | F59: Opening MRR | G59: New MRR | H59: Expansion MRR | I59: Contraction MRR | J59: Churn MRR | K59: Closing MRR
A60: 1 | B60: =SUMIFS(Data_MRR!$I:$I,Data_MRR!$B:$B,"B2C",Data_MRR!$A:$A,Assumptions!$B$10) | C60: =MAX($N$6,$N$6+$O$6*A60) | D60: =B60*$E$6 | E60: =B60-D60+C60 | F60: =SUMIFS(Data_MRR!$H:$H,Data_MRR!$B:$B,"B2C",Data_MRR!$A:$A,Assumptions!$B$10) | G60: =C60*$G$6 | H60: =F60*$I$6 | I60: =F60*$L$6 | J60: =F60*$E$6 | K60: =F60-J60+G60+H60-I60
A61: 2 | B61: =E60 | C61: =MAX($N$6,$N$6+$O$6*A61) | D61: =B61*$E$6 | E61: =B61-D61+C61 | F61: =K60 | G61: =C61*$G$6 | H61: =F61*$I$6 | I61: =F61*$L$6 | J61: =F61*$E$6 | K61: =F61-J61+G61+H61-I61
A62: 3 | B62: =E61 | C62: =MAX($N$6,$N$6+$O$6*A62) | D62: =B62*$E$6 | E62: =B62-D62+C62 | F62: =K61 | G62: =C62*$G$6 | H62: =F62*$I$6 | I62: =F62*$L$6 | J62: =F62*$E$6 | K62: =F62-J62+G62+H62-I62
A63: 4 | B63: =E62 | C63: =MAX($N$6,$N$6+$O$6*A63) | D63: =B63*$E$6 | E63: =B63-D63+C63 | F63: =K62 | G63: =C63*$G$6 | H63: =F63*$I$6 | I63: =F63*$L$6 | J63: =F63*$E$6 | K63: =F63-J63+G63+H63-I63
A64: 5 | B64: =E63 | C64: =MAX($N$6,$N$6+$O$6*A64) | D64: =B64*$E$6 | E64: =B64-D64+C64 | F64: =K63 | G64: =C64*$G$6 | H64: =F64*$I$6 | I64: =F64*$L$6 | J64: =F64*$E$6 | K64: =F64-J64+G64+H64-I64
A65: 6 | B65: =E64 | C65: =MAX($N$6,$N$6+$O$6*A65) | D65: =B65*$E$6 | E65: =B65-D65+C65 | F65: =K64 | G65: =C65*$G$6 | H65: =F65*$I$6 | I65: =F65*$L$6 | J65: =F65*$E$6 | K65: =F65-J65+G65+H65-I65
A66: 7 | B66: =E65 | C66: =MAX($N$6,$N$6+$O$6*A66) | D66: =B66*$E$6 | E66: =B66-D66+C66 | F66: =K65 | G66: =C66*$G$6 | H66: =F66*$I$6 | I66: =F66*$L$6 | J66: =F66*$E$6 | K66: =F66-J66+G66+H66-I66
A67: 8 | B67: =E66 | C67: =MAX($N$6,$N$6+$O$6*A67) | D67: =B67*$E$6 | E67: =B67-D67+C67 | F67: =K66 | G67: =C67*$G$6 | H67: =F67*$I$6 | I67: =F67*$L$6 | J67: =F67*$E$6 | K67: =F67-J67+G67+H67-I67
A68: 9 | B68: =E67 | C68: =MAX($N$6,$N$6+$O$6*A68) | D68: =B68*$E$6 | E68: =B68-D68+C68 | F68: =K67 | G68: =C68*$G$6 | H68: =F68*$I$6 | I68: =F68*$L$6 | J68: =F68*$E$6 | K68: =F68-J68+G68+H68-I68
A69: 10 | B69: =E68 | C69: =MAX($N$6,$N$6+$O$6*A69) | D69: =B69*$E$6 | E69: =B69-D69+C69 | F69: =K68 | G69: =C69*$G$6 | H69: =F69*$I$6 | I69: =F69*$L$6 | J69: =F69*$E$6 | K69: =F69-J69+G69+H69-I69
A70: 11 | B70: =E69 | C70: =MAX($N$6,$N$6+$O$6*A70) | D70: =B70*$E$6 | E70: =B70-D70+C70 | F70: =K69 | G70: =C70*$G$6 | H70: =F70*$I$6 | I70: =F70*$L$6 | J70: =F70*$E$6 | K70: =F70-J70+G70+H70-I70
A71: 12 | B71: =E70 | C71: =MAX($N$6,$N$6+$O$6*A71) | D71: =B71*$E$6 | E71: =B71-D71+C71 | F71: =K70 | G71: =C71*$G$6 | H71: =F71*$I$6 | I71: =F71*$L$6 | J71: =F71*$E$6 | K71: =F71-J71+G71+H71-I71
A73: Bull / SMB
A74: Month # | B74: Opening customers | C74: New customers | D74: Churn customers | E74: Closing customers | F74: Opening MRR | G74: New MRR | H74: Expansion MRR | I74: Contraction MRR | J74: Churn MRR | K74: Closing MRR
A75: 1 | B75: =SUMIFS(Data_MRR!$I:$I,Data_MRR!$B:$B,"SMB",Data_MRR!$A:$A,Assumptions!$B$10) | C75: =MAX($N$7,$N$7+$O$7*A75) | D75: =B75*$E$7 | E75: =B75-D75+C75 | F75: =SUMIFS(Data_MRR!$H:$H,Data_MRR!$B:$B,"SMB",Data_MRR!$A:$A,Assumptions!$B$10) | G75: =C75*$G$7 | H75: =F75*$I$7 | I75: =F75*$L$7 | J75: =F75*$E$7 | K75: =F75-J75+G75+H75-I75
A76: 2 | B76: =E75 | C76: =MAX($N$7,$N$7+$O$7*A76) | D76: =B76*$E$7 | E76: =B76-D76+C76 | F76: =K75 | G76: =C76*$G$7 | H76: =F76*$I$7 | I76: =F76*$L$7 | J76: =F76*$E$7 | K76: =F76-J76+G76+H76-I76
A77: 3 | B77: =E76 | C77: =MAX($N$7,$N$7+$O$7*A77) | D77: =B77*$E$7 | E77: =B77-D77+C77 | F77: =K76 | G77: =C77*$G$7 | H77: =F77*$I$7 | I77: =F77*$L$7 | J77: =F77*$E$7 | K77: =F77-J77+G77+H77-I77
A78: 4 | B78: =E77 | C78: =MAX($N$7,$N$7+$O$7*A78) | D78: =B78*$E$7 | E78: =B78-D78+C78 | F78: =K77 | G78: =C78*$G$7 | H78: =F78*$I$7 | I78: =F78*$L$7 | J78: =F78*$E$7 | K78: =F78-J78+G78+H78-I78
A79: 5 | B79: =E78 | C79: =MAX($N$7,$N$7+$O$7*A79) | D79: =B79*$E$7 | E79: =B79-D79+C79 | F79: =K78 | G79: =C79*$G$7 | H79: =F79*$I$7 | I79: =F79*$L$7 | J79: =F79*$E$7 | K79: =F79-J79+G79+H79-I79
A80: 6 | B80: =E79 | C80: =MAX($N$7,$N$7+$O$7*A80) | D80: =B80*$E$7 | E80: =B80-D80+C80 | F80: =K79 | G80: =C80*$G$7 | H80: =F80*$I$7 | I80: =F80*$L$7 | J80: =F80*$E$7 | K80: =F80-J80+G80+H80-I80
A81: 7 | B81: =E80 | C81: =MAX($N$7,$N$7+$O$7*A81) | D81: =B81*$E$7 | E81: =B81-D81+C81 | F81: =K80 | G81: =C81*$G$7 | H81: =F81*$I$7 | I81: =F81*$L$7 | J81: =F81*$E$7 | K81: =F81-J81+G81+H81-I81
A82: 8 | B82: =E81 | C82: =MAX($N$7,$N$7+$O$7*A82) | D82: =B82*$E$7 | E82: =B82-D82+C82 | F82: =K81 | G82: =C82*$G$7 | H82: =F82*$I$7 | I82: =F82*$L$7 | J82: =F82*$E$7 | K82: =F82-J82+G82+H82-I82
A83: 9 | B83: =E82 | C83: =MAX($N$7,$N$7+$O$7*A83) | D83: =B83*$E$7 | E83: =B83-D83+C83 | F83: =K82 | G83: =C83*$G$7 | H83: =F83*$I$7 | I83: =F83*$L$7 | J83: =F83*$E$7 | K83: =F83-J83+G83+H83-I83
A84: 10 | B84: =E83 | C84: =MAX($N$7,$N$7+$O$7*A84) | D84: =B84*$E$7 | E84: =B84-D84+C84 | F84: =K83 | G84: =C84*$G$7 | H84: =F84*$I$7 | I84: =F84*$L$7 | J84: =F84*$E$7 | K84: =F84-J84+G84+H84-I84
A85: 11 | B85: =E84 | C85: =MAX($N$7,$N$7+$O$7*A85) | D85: =B85*$E$7 | E85: =B85-D85+C85 | F85: =K84 | G85: =C85*$G$7 | H85: =F85*$I$7 | I85: =F85*$L$7 | J85: =F85*$E$7 | K85: =F85-J85+G85+H85-I85
A86: 12 | B86: =E85 | C86: =MAX($N$7,$N$7+$O$7*A86) | D86: =B86*$E$7 | E86: =B86-D86+C86 | F86: =K85 | G86: =C86*$G$7 | H86: =F86*$I$7 | I86: =F86*$L$7 | J86: =F86*$E$7 | K86: =F86-J86+G86+H86-I86
A88: Bull / Enterprise
A89: Month # | B89: Opening customers | C89: New customers | D89: Churn customers | E89: Closing customers | F89: Opening MRR | G89: New MRR | H89: Expansion MRR | I89: Contraction MRR | J89: Churn MRR | K89: Closing MRR
A90: 1 | B90: =SUMIFS(Data_MRR!$I:$I,Data_MRR!$B:$B,"Enterprise",Data_MRR!$A:$A,Assumptions!$B$10) | C90: =MAX($N$8,$N$8+$O$8*A90) | D90: =B90*$E$8 | E90: =B90-D90+C90 | F90: =SUMIFS(Data_MRR!$H:$H,Data_MRR!$B:$B,"Enterprise",Data_MRR!$A:$A,Assumptions!$B$10) | G90: =C90*$G$8 | H90: =F90*$I$8 | I90: =F90*$L$8 | J90: =F90*$E$8 | K90: =F90-J90+G90+H90-I90
A91: 2 | B91: =E90 | C91: =MAX($N$8,$N$8+$O$8*A91) | D91: =B91*$E$8 | E91: =B91-D91+C91 | F91: =K90 | G91: =C91*$G$8 | H91: =F91*$I$8 | I91: =F91*$L$8 | J91: =F91*$E$8 | K91: =F91-J91+G91+H91-I91
A92: 3 | B92: =E91 | C92: =MAX($N$8,$N$8+$O$8*A92) | D92: =B92*$E$8 | E92: =B92-D92+C92 | F92: =K91 | G92: =C92*$G$8 | H92: =F92*$I$8 | I92: =F92*$L$8 | J92: =F92*$E$8 | K92: =F92-J92+G92+H92-I92
A93: 4 | B93: =E92 | C93: =MAX($N$8,$N$8+$O$8*A93) | D93: =B93*$E$8 | E93: =B93-D93+C93 | F93: =K92 | G93: =C93*$G$8 | H93: =F93*$I$8 | I93: =F93*$L$8 | J93: =F93*$E$8 | K93: =F93-J93+G93+H93-I93
A94: 5 | B94: =E93 | C94: =MAX($N$8,$N$8+$O$8*A94) | D94: =B94*$E$8 | E94: =B94-D94+C94 | F94: =K93 | G94: =C94*$G$8 | H94: =F94*$I$8 | I94: =F94*$L$8 | J94: =F94*$E$8 | K94: =F94-J94+G94+H94-I94
A95: 6 | B95: =E94 | C95: =MAX($N$8,$N$8+$O$8*A95) | D95: =B95*$E$8 | E95: =B95-D95+C95 | F95: =K94 | G95: =C95*$G$8 | H95: =F95*$I$8 | I95: =F95*$L$8 | J95: =F95*$E$8 | K95: =F95-J95+G95+H95-I95
A96: 7 | B96: =E95 | C96: =MAX($N$8,$N$8+$O$8*A96) | D96: =B96*$E$8 | E96: =B96-D96+C96 | F96: =K95 | G96: =C96*$G$8 | H96: =F96*$I$8 | I96: =F96*$L$8 | J96: =F96*$E$8 | K96: =F96-J96+G96+H96-I96
A97: 8 | B97: =E96 | C97: =MAX($N$8,$N$8+$O$8*A97) | D97: =B97*$E$8 | E97: =B97-D97+C97 | F97: =K96 | G97: =C97*$G$8 | H97: =F97*$I$8 | I97: =F97*$L$8 | J97: =F97*$E$8 | K97: =F97-J97+G97+H97-I97
A98: 9 | B98: =E97 | C98: =MAX($N$8,$N$8+$O$8*A98) | D98: =B98*$E$8 | E98: =B98-D98+C98 | F98: =K97 | G98: =C98*$G$8 | H98: =F98*$I$8 | I98: =F98*$L$8 | J98: =F98*$E$8 | K98: =F98-J98+G98+H98-I98
A99: 10 | B99: =E98 | C99: =MAX($N$8,$N$8+$O$8*A99) | D99: =B99*$E$8 | E99: =B99-D99+C99 | F99: =K98 | G99: =C99*$G$8 | H99: =F99*$I$8 | I99: =F99*$L$8 | J99: =F99*$E$8 | K99: =F99-J99+G99+H99-I99
A100: 11 | B100: =E99 | C100: =MAX($N$8,$N$8+$O$8*A100) | D100: =B100*$E$8 | E100: =B100-D100+C100 | F100: =K99 | G100: =C100*$G$8 | H100: =F100*$I$8 | I100: =F100*$L$8 | J100: =F100*$E$8 | K100: =F100-J100+G100+H100-I100
A101: 12 | B101: =E100 | C101: =MAX($N$8,$N$8+$O$8*A101) | D101: =B101*$E$8 | E101: =B101-D101+C101 | F101: =K100 | G101: =C101*$G$8 | H101: =F101*$I$8 | I101: =F101*$L$8 | J101: =F101*$E$8 | K101: =F101-J101+G101+H101-I101
A104: Scenario: Bear -- 12-month projection by segment (May-24..Apr-25)
A105: Bear / B2C
A106: Month # | B106: Opening customers | C106: New customers | D106: Churn customers | E106: Closing customers | F106: Opening MRR | G106: New MRR | H106: Expansion MRR | I106: Contraction MRR | J106: Churn MRR | K106: Closing MRR
A107: 1 | B107: =SUMIFS(Data_MRR!$I:$I,Data_MRR!$B:$B,"B2C",Data_MRR!$A:$A,Assumptions!$B$10) | C107: =$N$6*(1-Assumptions!$B$64) | D107: =B107*$F$6 | E107: =B107-D107+C107 | F107: =SUMIFS(Data_MRR!$H:$H,Data_MRR!$B:$B,"B2C",Data_MRR!$A:$A,Assumptions!$B$10) | G107: =C107*$G$6 | H107: =F107*$J$6 | I107: =F107*$M$6 | J107: =F107*$F$6 | K107: =F107-J107+G107+H107-I107
A108: 2 | B108: =E107 | C108: =$N$6*(1-Assumptions!$B$64) | D108: =B108*$F$6 | E108: =B108-D108+C108 | F108: =K107 | G108: =C108*$G$6 | H108: =F108*$J$6 | I108: =F108*$M$6 | J108: =F108*$F$6 | K108: =F108-J108+G108+H108-I108
A109: 3 | B109: =E108 | C109: =$N$6*(1-Assumptions!$B$64) | D109: =B109*$F$6 | E109: =B109-D109+C109 | F109: =K108 | G109: =C109*$G$6 | H109: =F109*$J$6 | I109: =F109*$M$6 | J109: =F109*$F$6 | K109: =F109-J109+G109+H109-I109
A110: 4 | B110: =E109 | C110: =$N$6*(1-Assumptions!$B$64) | D110: =B110*$F$6 | E110: =B110-D110+C110 | F110: =K109 | G110: =C110*$G$6 | H110: =F110*$J$6 | I110: =F110*$M$6 | J110: =F110*$F$6 | K110: =F110-J110+G110+H110-I110
...

Sheet Strategies
A1: Strategies
A2: Source: WP23 results.md + mart_s_04_strategy_impact (from the Python scenario engine, sql/python_models/scenarios.py -- each strategy is sized as an isolated lever on top of the Base scenario). The company-wide 6mo/12mo MRR and NDR deltas are simulation outputs ('from engine', not spreadsheet formulas -- the underlying monthly compartment simulation is not re-derived here, same as the Scenarios tab's engine comparison). One illustrative figure IS a simple in-sheet formula: Strategy-1's immediate monthly save on the concrete May-24 at-risk list.
A4: Illustrative simple-formula check: Strategy-1 applied to the May-24 at-risk list (source: mart_a1_06_may24_churn_risk, D-16 risk tiers)
A5: Metric | B5: Value | C5: Unit | D5: Source
A6: May-24 High+Medium risk MRR (flagged) | B6: =Assumptions!$B$77 | C6: USD | D6: Assumptions (mart_a1_06_may24_churn_risk)
A7: ...of which expected to churn (mrr_at_risk) | B7: =Assumptions!$B$78 | C7: USD | D7: Assumptions (mart_a1_06_may24_churn_risk)
A8: Strategy-1 base-case save rate (link to Assumptions) | B8: =Assumptions!$B$71 | C8: fraction saved | D8: A-20 (Assumptions)
A9: -> Immediate monthly MRR saved if applied once to the May-24 list | B9: =B7*B8 | C9: USD/month | D9: simple formula (at-risk MRR x save rate)
A11: This single-month figure is smaller than the engine's $7,690/6-month company number below because the engine compounds the same save rate over every month's newly flagged cohort, not just the May-24 list once (see WP23 results.md).
A13: Company-wide strategy impact, low/base/high (from engine: mart_s_04_strategy_impact)
A14: Strategy | B14: Case | C14: 6-mo MRR impact ($) | D14: 6-mo MRR impact (%) | E14: 12-mo MRR impact ($) | F14: NDR impact, 6-mo (pp) | G14: Effort | H14: Time to impact (months)
A15: 1. Engagement alert + save play | B15: low | C15: 3763.0281 | D15: 0.013269798 | E15: 6607.6738 | F15: 1.3113409 | G15: Low | H15: 1
A16: 1. Engagement alert + save play | B16: base | C16: 7690.0102 | D16: 0.027117757 | E16: 13783.118 | F16: 2.6890724 | G16: Low | H16: 1
A17: 1. Engagement alert + save play | B17: high | C17: 11787.322 | D17: 0.041566362 | E17: 21578.618 | F17: 4.1359909 | G17: Low | H17: 1
A18: 2. B2C monthly -> annual migration | B18: low | C18: -455.90918 | D18: -0.0016077007 | E18: 754.72421 | F18: -0.10351744 | G18: Medium | H18: 6
A19: 2. B2C monthly -> annual migration | B19: base | C19: -849.63982 | D19: -0.0029961373 | E19: 1529.2761 | F19: -0.1837432 | G19: Medium | H19: 6
A20: 2. B2C monthly -> annual migration | B20: high | C20: -1186.6522 | D20: -0.004184565 | E20: 2308.591 | F20: -0.2430074 | G20: Medium | H20: 6
A21: 3. B2B expansion/contraction playbook | B21: low | C21: 810.33067 | D21: 0.002857519 | E21: 1828.8675 | F21: 0.31637505 | G21: Medium | H21: 3
A22: 3. B2B expansion/contraction playbook | B22: base | C22: 1559.3557 | D22: 0.0054988523 | E22: 3528.9993 | F22: 0.60887707 | G22: Medium | H22: 3
A23: 3. B2B expansion/contraction playbook | B23: high | C23: 2313.3976 | D23: 0.0081578767 | E23: 5252.8431 | F23: 0.9035438 | G23: Medium | H23: 3
A25: Recommended sequence (WP23; unchanged narrative from the engine's own numbers above)
A26: 1) Engagement alert (Strategy 1) -- ship first: cheapest, fastest, biggest single lever (Low effort, 1 month to impact).
A27: 2) B2B playbook (Strategy 3) -- run in parallel: positive, no MRR downside, Medium effort.
A28: 3) Annual migration offer (Strategy 2) -- sequence third: costs MRR for ~9 months before it pays back (see mrr_delta_pct_m6 above is negative for this strategy).

Sheet Checks
A1: Checks
A2: TRUE/FALSE reconciliation checks. The master cell below is TRUE only if every check in every section passes.
A4: ALL CHECKS PASS | B4: =IF(COUNTIF(B6:B27,FALSE)=0,"TRUE -- all checks pass","FALSE -- see failing rows below")
A6: MRR bridge identity -- every month, opening+new+exp-contr-churn=closing (Data_MRR)
A7: All 80 Data_MRR rows satisfy the bridge identity | B7: =COUNTIF(Data_MRR!$J$5:$J$84,FALSE)=0 | C7: COUNTIF of the Data_MRR!J bridge_check column
A9: Q1 / Q3 totals
A10: Q1 total MRR Apr-24 = 204,709.09 (sum of segments) | B10: =ROUND(Answers_Q1_Q4!$B$9,2)=ROUND(Assumptions!$B$24,2) | C10: Answers_Q1_Q4 Q1 total vs. Assumptions QA target
A11: Q3 total active subs Apr-24 = 1,941 | B11: =Answers_Q1_Q4!$D$47=Assumptions!$B$25 | C11: Answers_Q1_Q4 Q3 total vs. Assumptions QA target
A13: CAC and LTV match mart_a2_12_unit_economics_summary within 1% (T6M basis, 60-month cap)
A14: B2C: sheet CAC (T6M) vs. mart_a2_12 within 1% | B14: =ABS(UnitEconomics!$H$28-INDEX(Assumptions!$C$202:$C$300,MATCH("A2-043",Assumptions!$A$202:$A$300,0)))/INDEX(Assumptions!$C$202:$C$300,MATCH("A2-043",Assumptions!$A$202:$A$300,0))<=Assumptions!$B$23 | C14: Assumptions register A2-043
A15: B2C: sheet LTV (60mo cap, T6M GM) vs. mart_a2_12 within 1% | B15: =ABS(UnitEconomics!$N$28-INDEX(Assumptions!$C$202:$C$300,MATCH("A2-051",Assumptions!$A$202:$A$300,0)))/INDEX(Assumptions!$C$202:$C$300,MATCH("A2-051",Assumptions!$A$202:$A$300,0))<=Assumptions!$B$23 | C15: Assumptions register A2-051; valid when the GM-basis selector = 'T6M avg'
A16: SMB: sheet CAC (T6M) vs. mart_a2_12 within 1% | B16: =ABS(UnitEconomics!$H$29-INDEX(Assumptions!$C$202:$C$300,MATCH("A2-058",Assumptions!$A$202:$A$300,0)))/INDEX(Assumptions!$C$202:$C$300,MATCH("A2-058",Assumptions!$A$202:$A$300,0))<=Assumptions!$B$23 | C16: Assumptions register A2-058
A17: SMB: sheet LTV (60mo cap, T6M GM) vs. mart_a2_12 within 1% | B17: =ABS(UnitEconomics!$N$29-INDEX(Assumptions!$C$202:$C$300,MATCH("A2-066",Assumptions!$A$202:$A$300,0)))/INDEX(Assumptions!$C$202:$C$300,MATCH("A2-066",Assumptions!$A$202:$A$300,0))<=Assumptions!$B$23 | C17: Assumptions register A2-066; valid when the GM-basis selector = 'T6M avg'
A18: Enterprise: sheet CAC (T6M) vs. mart_a2_12 within 1% | B18: =ABS(UnitEconomics!$H$30-INDEX(Assumptions!$C$202:$C$300,MATCH("A2-073",Assumptions!$A$202:$A$300,0)))/INDEX(Assumptions!$C$202:$C$300,MATCH("A2-073",Assumptions!$A$202:$A$300,0))<=Assumptions!$B$23 | C18: Assumptions register A2-073
A19: Enterprise: sheet LTV (60mo cap, T6M GM) vs. mart_a2_12 within 1% | B19: =ABS(UnitEconomics!$N$30-INDEX(Assumptions!$C$202:$C$300,MATCH("A2-081",Assumptions!$A$202:$A$300,0)))/INDEX(Assumptions!$C$202:$C$300,MATCH("A2-081",Assumptions!$A$202:$A$300,0))<=Assumptions!$B$23 | C19: Assumptions register A2-081; valid when the GM-basis selector = 'T6M avg'
A21: Scenario reconciliation -- Sheet vs. engine within tolerance (Scenarios tab)
A22: All Sheet-vs-engine scenario deltas are within tolerance | B22: =COUNTIF(Scenarios!$F$160:$F$171,FALSE)=0 | C22: Scenarios!F column, tolerance = Assumptions tol_scenario (3%)
A24: Retention-adjusted payback sanity (resolves the WP40 open issue: computed on the full 60-month curve, not just the observed horizon)
A25: Retention-adjusted payback is populated (a number or '> 60') for B2C/SMB/Enterprise | B25: =COUNTIF(UnitEconomics!$C$98:$C$100,"")=0 | C25: UnitEconomics payback block, column C
